[
    {
        "index_right":"1087",
        "Text_Clean":"3002",
        "ID":"10",
        "ToBD":"23",
        "ThuaTam":"",
        "TCT":"3002",
        "SHKhu":"",
        "SHKhoanh":"",
        "MaLD":"",
        "LRD":"DGT",
        "TTRung":"",
        "DienTichThuc":"5763.909698260162",
        "DienTich":"5763.9",
        "dtThocu":"0.0",
        "DienTichThuHoi":"0.0",
        "TenChu":"UBND phường quản lý",
        "TenVC":"",
        "DTSD":"0",
        "DiaChi":"",
        "Xudong":"Khu phố 10",
        "TamX":"442323.84",
        "TamY":"1131377.27",
        "XMin":"0.0",
        "YMin":"0.0",
        "XMax":"0.0",
        "YMax":"0.0",
        "GhiChu":"",
        "CapNhat":"True",
        "LenPoly":"640.92",
        "DTMuonTam":"0.0",
        "MaXaID":"0",
        "KhuDanCu":"False",
        "DatDoThi":"False",
        "DiaChiThuaDatChiTiet":"",
        "NguonGocHinhThanh":"",
        "ThoiDiemHinhThanh":"",
        "SoHieuToBanDoGoc":"",
        "ChuaGiaoDat":"True",
        "ThuaDatId":"10",
        "SoHieuThua2":"",
        "ToBDCu":"",
        "TCTCu":"",
        "DienTichCu":"0.0",
        "LoaiDatCu":"",
        "GhiChu2":"",
        "DTPhapLy":"5763.9",
        "MaChuSDID":"0",
        "LoaiDatKiemKe":"",
        "KyHieuDTSD":"",
        "maThua":"",
        "inSoLieuCu":"False",
        "hangDat":"0",
        "trangThai":"False",
        "saoLuuId":"0",
        "taiLieuDoDacId":"0",
        "sttThuaGoc":"",
        "maThua_clean":"3002",
        "latitude":10.2313941729,
        "longitude":103.9739492198,
        "polygon":[
            [
                10.2313775564,
                103.9733434667
            ],
            [
                10.2315673282,
                103.9741351875
            ],
            [
                10.2315891939,
                103.9746185538
            ],
            [
                10.2315901941,
                103.9746192491
            ],
            [
                10.2316547247,
                103.9746105146
            ],
            [
                10.2316638997,
                103.9751059559
            ],
            [
                10.2315877817,
                103.9751085613
            ],
            [
                10.2315871615,
                103.9751093592
            ],
            [
                10.2315855236,
                103.9751309748
            ],
            [
                10.2315520228,
                103.9751310298
            ],
            [
                10.2315519977,
                103.9751181613
            ],
            [
                10.2315510965,
                103.9751173395
            ],
            [
                10.2315501981,
                103.9751181643
            ],
            [
                10.2315502145,
                103.9751310328
            ],
            [
                10.231462991,
                103.9751311761
            ],
            [
                10.2314641446,
                103.975077488
            ],
            [
                10.2314579518,
                103.9747129719
            ],
            [
                10.2314599863,
                103.9746854577
            ],
            [
                10.2314551594,
                103.974226526
            ],
            [
                10.2313035299,
                103.9737283299
            ],
            [
                10.2312756874,
                103.9736183918
            ],
            [
                10.2312436677,
                103.9734985033
            ],
            [
                10.2312272989,
                103.9734414729
            ],
            [
                10.2311980066,
                103.9733313443
            ],
            [
                10.2311557287,
                103.9731811044
            ],
            [
                10.2311441525,
                103.973127246
            ],
            [
                10.2311090007,
                103.9730291632
            ],
            [
                10.2311004288,
                103.972992627
            ],
            [
                10.2310472028,
                103.9728517139
            ],
            [
                10.2310944639,
                103.9728516359
            ],
            [
                10.2310944891,
                103.9728645044
            ],
            [
                10.2310953902,
                103.9728653262
            ],
            [
                10.2310962887,
                103.9728645014
            ],
            [
                10.2310962722,
                103.9728516329
            ],
            [
                10.231266503,
                103.9728513521
            ],
            [
                10.231271921,
                103.9728781077
            ],
            [
                10.2313775564,
                103.9733434667
            ]
        ]
    },
    {
        "index_right":"1068",
        "Text_Clean":"17",
        "ID":"20",
        "ToBD":"23",
        "ThuaTam":"",
        "TCT":"17",
        "SHKhu":"",
        "SHKhoanh":"",
        "MaLD":"",
        "LRD":"CLN",
        "TTRung":"",
        "DienTichThuc":"147.2074000025168",
        "DienTich":"147.2",
        "dtThocu":"0.0",
        "DienTichThuHoi":"0.0",
        "TenChu":"Võ Thị Mỹ Lệ",
        "TenVC":"",
        "DTSD":"0",
        "DiaChi":"",
        "Xudong":"Khu phố 10",
        "TamX":"442395.38",
        "TamY":"1131371.73",
        "XMin":"0.0",
        "YMin":"0.0",
        "XMax":"0.0",
        "YMax":"0.0",
        "GhiChu":"DacapGCN",
        "CapNhat":"True",
        "LenPoly":"72.21",
        "DTMuonTam":"0.0",
        "MaXaID":"0",
        "KhuDanCu":"False",
        "DatDoThi":"False",
        "DiaChiThuaDatChiTiet":"",
        "NguonGocHinhThanh":"",
        "ThoiDiemHinhThanh":"",
        "SoHieuToBanDoGoc":"",
        "ChuaGiaoDat":"True",
        "ThuaDatId":"20",
        "SoHieuThua2":"",
        "ToBDCu":"",
        "TCTCu":"",
        "DienTichCu":"0.0",
        "LoaiDatCu":"",
        "GhiChu2":"",
        "DTPhapLy":"147.1",
        "MaChuSDID":"0",
        "LoaiDatKiemKe":"",
        "KyHieuDTSD":"",
        "maThua":"",
        "inSoLieuCu":"False",
        "hangDat":"0",
        "trangThai":"False",
        "saoLuuId":"0",
        "taiLieuDoDacId":"0",
        "sttThuaGoc":"",
        "maThua_clean":"17",
        "latitude":10.2312926502,
        "longitude":103.974177733,
        "polygon":[
            [
                10.2313573208,
                103.9741462422
            ],
            [
                10.2313677306,
                103.9741862174
            ],
            [
                10.2311559415,
                103.9742205827
            ],
            [
                10.2311502518,
                103.9741803186
            ],
            [
                10.2313573208,
                103.9741462422
            ]
        ]
    },
    {
        "index_right":"1065",
        "Text_Clean":"16",
        "ID":"19",
        "ToBD":"23",
        "ThuaTam":"",
        "TCT":"16",
        "SHKhu":"",
        "SHKhoanh":"",
        "MaLD":"",
        "LRD":"CLN",
        "TTRung":"",
        "DienTichThuc":"147.6444999985979",
        "DienTich":"147.6",
        "dtThocu":"0.0",
        "DienTichThuHoi":"0.0",
        "TenChu":"Võ Thị Mỹ Tiên",
        "TenVC":"",
        "DTSD":"0",
        "DiaChi":"",
        "Xudong":"Khu phố 10",
        "TamX":"442390.74",
        "TamY":"1131370.67",
        "XMin":"0.0",
        "YMin":"0.0",
        "XMax":"0.0",
        "YMax":"0.0",
        "GhiChu":"DacapGCN",
        "CapNhat":"True",
        "LenPoly":"71.0",
        "DTMuonTam":"0.0",
        "MaXaID":"0",
        "KhuDanCu":"False",
        "DatDoThi":"False",
        "DiaChiThuaDatChiTiet":"",
        "NguonGocHinhThanh":"",
        "ThoiDiemHinhThanh":"",
        "SoHieuToBanDoGoc":"",
        "ChuaGiaoDat":"True",
        "ThuaDatId":"19",
        "SoHieuThua2":"",
        "ToBDCu":"",
        "TCTCu":"",
        "DienTichCu":"0.0",
        "LoaiDatCu":"",
        "GhiChu2":"",
        "DTPhapLy":"147.7",
        "MaChuSDID":"0",
        "LoaiDatKiemKe":"",
        "KyHieuDTSD":"",
        "maThua":"",
        "inSoLieuCu":"False",
        "hangDat":"0",
        "trangThai":"False",
        "saoLuuId":"0",
        "taiLieuDoDacId":"0",
        "sttThuaGoc":"",
        "maThua_clean":"16",
        "latitude":10.2312801529,
        "longitude":103.9741357972,
        "polygon":[
            [
                10.2313465303,
                103.9741048053
            ],
            [
                10.2313568589,
                103.9741444685
            ],
            [
                10.2311499952,
                103.9741785111
            ],
            [
                10.231143671,
                103.9741341593
            ],
            [
                10.2313465303,
                103.9741048053
            ]
        ]
    },
    {
        "index_right":"976",
        "Text_Clean":"34",
        "ID":"18",
        "ToBD":"23",
        "ThuaTam":"",
        "TCT":"34",
        "SHKhu":"",
        "SHKhoanh":"",
        "MaLD":"",
        "LRD":"CLN",
        "TTRung":"",
        "DienTichThuc":"174.62865000101738",
        "DienTich":"174.6",
        "dtThocu":"0.0",
        "DienTichThuHoi":"0.0",
        "TenChu":"Võ Thị Kiều Nhi",
        "TenVC":"",
        "DTSD":"0",
        "DiaChi":"",
        "Xudong":"Khu phố 10",
        "TamX":"442385.51",
        "TamY":"1131369.58",
        "XMin":"0.0",
        "YMin":"0.0",
        "XMax":"0.0",
        "YMax":"0.0",
        "GhiChu":"DacapGCN",
        "CapNhat":"True",
        "LenPoly":"71.46",
        "DTMuonTam":"0.0",
        "MaXaID":"0",
        "KhuDanCu":"False",
        "DatDoThi":"False",
        "DiaChiThuaDatChiTiet":"",
        "NguonGocHinhThanh":"",
        "ThoiDiemHinhThanh":"",
        "SoHieuToBanDoGoc":"",
        "ChuaGiaoDat":"True",
        "ThuaDatId":"18",
        "SoHieuThua2":"",
        "ToBDCu":"",
        "TCTCu":"",
        "DienTichCu":"0.0",
        "LoaiDatCu":"",
        "GhiChu2":"",
        "DTPhapLy":"174.6",
        "MaChuSDID":"0",
        "LoaiDatKiemKe":"",
        "KyHieuDTSD":"",
        "maThua":"",
        "inSoLieuCu":"False",
        "hangDat":"0",
        "trangThai":"False",
        "saoLuuId":"0",
        "taiLieuDoDacId":"0",
        "sttThuaGoc":"",
        "maThua_clean":"34",
        "latitude":10.2312721007,
        "longitude":103.9740878092,
        "polygon":[
            [
                10.2313330422,
                103.974053009
            ],
            [
                10.2313460675,
                103.974103028
            ],
            [
                10.2311434135,
                103.9741323523
            ],
            [
                10.2311360809,
                103.9740808678
            ],
            [
                10.2313330422,
                103.974053009
            ]
        ]
    },
    {
        "index_right":"1071",
        "Text_Clean":"15",
        "ID":"17",
        "ToBD":"23",
        "ThuaTam":"",
        "TCT":"15",
        "SHKhu":"",
        "SHKhoanh":"",
        "MaLD":"",
        "LRD":"CLN",
        "TTRung":"",
        "DienTichThuc":"140.39695000019856",
        "DienTich":"140.4",
        "dtThocu":"0.0",
        "DienTichThuHoi":"0.0",
        "TenChu":"Võ Thị Kim Dung",
        "TenVC":"",
        "DTSD":"0",
        "DiaChi":"",
        "Xudong":"Khu phố 10",
        "TamX":"442380.3",
        "TamY":"1131368.34",
        "XMin":"0.0",
        "YMin":"0.0",
        "XMax":"0.0",
        "YMax":"0.0",
        "GhiChu":"DacapGCN",
        "CapNhat":"True",
        "LenPoly":"67.86",
        "DTMuonTam":"0.0",
        "MaXaID":"0",
        "KhuDanCu":"False",
        "DatDoThi":"False",
        "DiaChiThuaDatChiTiet":"",
        "NguonGocHinhThanh":"",
        "ThoiDiemHinhThanh":"",
        "SoHieuToBanDoGoc":"",
        "ChuaGiaoDat":"True",
        "ThuaDatId":"17",
        "SoHieuThua2":"",
        "ToBDCu":"",
        "TCTCu":"",
        "DienTichCu":"0.0",
        "LoaiDatCu":"",
        "GhiChu2":"",
        "DTPhapLy":"140.5",
        "MaChuSDID":"0",
        "LoaiDatKiemKe":"",
        "KyHieuDTSD":"",
        "maThua":"",
        "inSoLieuCu":"False",
        "hangDat":"0",
        "trangThai":"False",
        "saoLuuId":"0",
        "taiLieuDoDacId":"0",
        "sttThuaGoc":"",
        "maThua_clean":"15",
        "latitude":10.2312569604,
        "longitude":103.974040542,
        "polygon":[
            [
                10.2313224831,
                103.9740124605
            ],
            [
                10.2313325792,
                103.9740512311
            ],
            [
                10.2311358234,
                103.9740790609
            ],
            [
                10.231129136,
                103.974032172
            ],
            [
                10.2313224831,
                103.9740124605
            ]
        ]
    },
    {
        "index_right":"975",
        "Text_Clean":"14",
        "ID":"16",
        "ToBD":"23",
        "ThuaTam":"",
        "TCT":"14",
        "SHKhu":"",
        "SHKhoanh":"",
        "MaLD":"",
        "LRD":"CLN",
        "TTRung":"",
        "DienTichThuc":"137.2707999998238",
        "DienTich":"137.3",
        "dtThocu":"0.0",
        "DienTichThuHoi":"0.0",
        "TenChu":"Võ Thị Mỹ Ngọc",
        "TenVC":"",
        "DTSD":"0",
        "DiaChi":"",
        "Xudong":"Khu phố 10",
        "TamX":"442375.53",
        "TamY":"1131367.36",
        "XMin":"0.0",
        "YMin":"0.0",
        "XMax":"0.0",
        "YMax":"0.0",
        "GhiChu":"DacapGCN",
        "CapNhat":"True",
        "LenPoly":"66.47",
        "DTMuonTam":"0.0",
        "MaXaID":"0",
        "KhuDanCu":"False",
        "DatDoThi":"False",
        "DiaChiThuaDatChiTiet":"",
        "NguonGocHinhThanh":"",
        "ThoiDiemHinhThanh":"",
        "SoHieuToBanDoGoc":"",
        "ChuaGiaoDat":"True",
        "ThuaDatId":"16",
        "SoHieuThua2":"",
        "ToBDCu":"",
        "TCTCu":"",
        "DienTichCu":"0.0",
        "LoaiDatCu":"",
        "GhiChu2":"",
        "DTPhapLy":"137.2",
        "MaChuSDID":"0",
        "LoaiDatKiemKe":"",
        "KyHieuDTSD":"",
        "maThua":"",
        "inSoLieuCu":"False",
        "hangDat":"0",
        "trangThai":"False",
        "saoLuuId":"0",
        "taiLieuDoDacId":"0",
        "sttThuaGoc":"",
        "maThua_clean":"14",
        "latitude":10.2312528244,
        "longitude":103.9739965313,
        "polygon":[
            [
                10.231311168,
                103.9739690093
            ],
            [
                10.2313220176,
                103.9740106731
            ],
            [
                10.2311288776,
                103.9740303635
            ],
            [
                10.2311229178,
                103.9739887309
            ],
            [
                10.231311168,
                103.9739690093
            ]
        ]
    },
    {
        "index_right":"973",
        "Text_Clean":"12",
        "ID":"14",
        "ToBD":"23",
        "ThuaTam":"",
        "TCT":"12",
        "SHKhu":"",
        "SHKhoanh":"",
        "MaLD":"",
        "LRD":"CLN",
        "TTRung":"",
        "DienTichThuc":"124.61444999824744",
        "DienTich":"124.6",
        "dtThocu":"0.0",
        "DienTichThuHoi":"0.0",
        "TenChu":"Võ Thị Kiều Oanh",
        "TenVC":"",
        "DTSD":"0",
        "DiaChi":"",
        "Xudong":"Khu phố 10",
        "TamX":"442355.89",
        "TamY":"1131362.94",
        "XMin":"0.0",
        "YMin":"0.0",
        "XMax":"0.0",
        "YMax":"0.0",
        "GhiChu":"DacapGCN",
        "CapNhat":"True",
        "LenPoly":"60.18",
        "DTMuonTam":"0.0",
        "MaXaID":"0",
        "KhuDanCu":"False",
        "DatDoThi":"False",
        "DiaChiThuaDatChiTiet":"",
        "NguonGocHinhThanh":"",
        "ThoiDiemHinhThanh":"",
        "SoHieuToBanDoGoc":"",
        "ChuaGiaoDat":"True",
        "ThuaDatId":"14",
        "SoHieuThua2":"",
        "ToBDCu":"",
        "TCTCu":"",
        "DienTichCu":"0.0",
        "LoaiDatCu":"",
        "GhiChu2":"",
        "DTPhapLy":"124.6",
        "MaChuSDID":"0",
        "LoaiDatKiemKe":"",
        "KyHieuDTSD":"",
        "maThua":"",
        "inSoLieuCu":"False",
        "hangDat":"0",
        "trangThai":"False",
        "saoLuuId":"0",
        "taiLieuDoDacId":"0",
        "sttThuaGoc":"",
        "maThua_clean":"12",
        "latitude":10.2312120112,
        "longitude":103.9738174671,
        "polygon":[
            [
                10.2312641628,
                103.9737885028
            ],
            [
                10.2312751679,
                103.973830764
            ],
            [
                10.2311038147,
                103.9738539342
            ],
            [
                10.2310975824,
                103.9738105711
            ],
            [
                10.2312641628,
                103.9737885028
            ]
        ]
    },
    {
        "index_right":"972",
        "Text_Clean":"11",
        "ID":"13",
        "ToBD":"23",
        "ThuaTam":"",
        "TCT":"11",
        "SHKhu":"",
        "SHKhoanh":"",
        "MaLD":"",
        "LRD":"CLN",
        "TTRung":"",
        "DienTichThuc":"242.71290000062436",
        "DienTich":"242.7",
        "dtThocu":"0.0",
        "DienTichThuHoi":"0.0",
        "TenChu":"Hồ Ánh Nguyệt",
        "TenVC":"",
        "DTSD":"0",
        "DiaChi":"",
        "Xudong":"Khu phố 10",
        "TamX":"442351.87",
        "TamY":"1131351.52",
        "XMin":"0.0",
        "YMin":"0.0",
        "XMax":"0.0",
        "YMax":"0.0",
        "GhiChu":"DacapGCN",
        "CapNhat":"True",
        "LenPoly":"93.58",
        "DTMuonTam":"0.0",
        "MaXaID":"0",
        "KhuDanCu":"False",
        "DatDoThi":"False",
        "DiaChiThuaDatChiTiet":"",
        "NguonGocHinhThanh":"",
        "ThoiDiemHinhThanh":"",
        "SoHieuToBanDoGoc":"",
        "ChuaGiaoDat":"True",
        "ThuaDatId":"13",
        "SoHieuThua2":"",
        "ToBDCu":"",
        "TCTCu":"",
        "DienTichCu":"0.0",
        "LoaiDatCu":"",
        "GhiChu2":"",
        "DTPhapLy":"242.6",
        "MaChuSDID":"0",
        "LoaiDatKiemKe":"",
        "KyHieuDTSD":"",
        "maThua":"",
        "inSoLieuCu":"False",
        "hangDat":"0",
        "trangThai":"False",
        "saoLuuId":"0",
        "taiLieuDoDacId":"0",
        "sttThuaGoc":"",
        "maThua_clean":"11",
        "latitude":10.2311082013,
        "longitude":103.9737809606,
        "polygon":[
            [
                10.2312505312,
                103.9737361559
            ],
            [
                10.2312636993,
                103.9737867229
            ],
            [
                10.2309315173,
                103.9738308552
            ],
            [
                10.2309226036,
                103.9737782733
            ],
            [
                10.2312505312,
                103.9737361559
            ]
        ]
    },
    {
        "index_right":"965",
        "Text_Clean":"2",
        "ID":"2",
        "ToBD":"23",
        "ThuaTam":"",
        "TCT":"2",
        "SHKhu":"",
        "SHKhoanh":"",
        "MaLD":"",
        "LRD":"ODT+CLN",
        "TTRung":"",
        "DienTichThuc":"476.2983000036329",
        "DienTich":"476.3",
        "dtThocu":"0.0",
        "DienTichThuHoi":"0.0",
        "TenChu":"Hồ Thị Kim Oanh",
        "TenVC":"",
        "DTSD":"0",
        "DiaChi":"",
        "Xudong":"Khu phố 10",
        "TamX":"442276.75",
        "TamY":"1131334.14",
        "XMin":"0.0",
        "YMin":"0.0",
        "XMax":"0.0",
        "YMax":"0.0",
        "GhiChu":"DacapGCN",
        "CapNhat":"True",
        "LenPoly":"95.53",
        "DTMuonTam":"0.0",
        "MaXaID":"0",
        "KhuDanCu":"False",
        "DatDoThi":"False",
        "DiaChiThuaDatChiTiet":"",
        "NguonGocHinhThanh":"",
        "ThoiDiemHinhThanh":"",
        "SoHieuToBanDoGoc":"",
        "ChuaGiaoDat":"True",
        "ThuaDatId":"2",
        "SoHieuThua2":"",
        "ToBDCu":"",
        "TCTCu":"",
        "DienTichCu":"0.0",
        "LoaiDatCu":"",
        "GhiChu2":"",
        "DTPhapLy":"476.2",
        "MaChuSDID":"0",
        "LoaiDatKiemKe":"",
        "KyHieuDTSD":"",
        "maThua":"",
        "inSoLieuCu":"False",
        "hangDat":"0",
        "trangThai":"False",
        "saoLuuId":"0",
        "taiLieuDoDacId":"0",
        "sttThuaGoc":"",
        "maThua_clean":"2",
        "latitude":10.230952625,
        "longitude":103.973095953,
        "polygon":[
            [
                10.2307974909,
                103.9731057238
            ],
            [
                10.2307911572,
                103.9730691547
            ],
            [
                10.231061952,
                103.9730030423
            ],
            [
                10.2310940826,
                103.9731353107
            ],
            [
                10.2308115679,
                103.9731856743
            ],
            [
                10.2307974909,
                103.9731057238
            ]
        ]
    },
    {
        "index_right":"1050",
        "Text_Clean":"36",
        "ID":"4",
        "ToBD":"23",
        "ThuaTam":"",
        "TCT":"36",
        "SHKhu":"",
        "SHKhoanh":"",
        "MaLD":"",
        "LRD":"CLN",
        "TTRung":"",
        "DienTichThuc":"162.96907296730205",
        "DienTich":"163.0",
        "dtThocu":"0.0",
        "DienTichThuHoi":"0.0",
        "TenChu":"Nguyễn Quốc Trung",
        "TenVC":"",
        "DTSD":"0",
        "DiaChi":"",
        "Xudong":"Khu phố 10",
        "TamX":"442291.96",
        "TamY":"1131337.2",
        "XMin":"0.0",
        "YMin":"0.0",
        "XMax":"0.0",
        "YMax":"0.0",
        "GhiChu":"DacapGCN",
        "CapNhat":"True",
        "LenPoly":"78.71",
        "DTMuonTam":"0.0",
        "MaXaID":"0",
        "KhuDanCu":"False",
        "DatDoThi":"False",
        "DiaChiThuaDatChiTiet":"",
        "NguonGocHinhThanh":"",
        "ThoiDiemHinhThanh":"",
        "SoHieuToBanDoGoc":"",
        "ChuaGiaoDat":"True",
        "ThuaDatId":"4",
        "SoHieuThua2":"",
        "ToBDCu":"",
        "TCTCu":"",
        "DienTichCu":"0.0",
        "LoaiDatCu":"",
        "GhiChu2":"",
        "DTPhapLy":"118.1",
        "MaChuSDID":"0",
        "LoaiDatKiemKe":"",
        "KyHieuDTSD":"",
        "maThua":"",
        "inSoLieuCu":"False",
        "hangDat":"0",
        "trangThai":"False",
        "saoLuuId":"0",
        "taiLieuDoDacId":"0",
        "sttThuaGoc":"",
        "maThua_clean":"36",
        "latitude":10.2309796414,
        "longitude":103.9732340268,
        "polygon":[
            [
                10.2309067126,
                103.9732261751
            ],
            [
                10.2311083238,
                103.9731900635
            ],
            [
                10.2311187398,
                103.9732300623
            ],
            [
                10.230829939,
                103.9732815709
            ],
            [
                10.2308225554,
                103.9732411256
            ],
            [
                10.2309067126,
                103.9732261751
            ]
        ]
    },
    {
        "index_right":"982",
        "Text_Clean":"1",
        "ID":"1",
        "ToBD":"23",
        "ThuaTam":"",
        "TCT":"1",
        "SHKhu":"",
        "SHKhoanh":"",
        "MaLD":"",
        "LRD":"ODT+CLN",
        "TTRung":"",
        "DienTichThuc":"550.4448999993037",
        "DienTich":"550.4",
        "dtThocu":"0.0",
        "DienTichThuHoi":"0.0",
        "TenChu":"Quảng Trọng Sang",
        "TenVC":"",
        "DTSD":"0",
        "DiaChi":"",
        "Xudong":"Khu phố 10",
        "TamX":"442261.74",
        "TamY":"1131330.52",
        "XMin":"0.0",
        "YMin":"0.0",
        "XMax":"0.0",
        "YMax":"0.0",
        "GhiChu":"DacapGCN",
        "CapNhat":"True",
        "LenPoly":"98.94",
        "DTMuonTam":"0.0",
        "MaXaID":"0",
        "KhuDanCu":"False",
        "DatDoThi":"False",
        "DiaChiThuaDatChiTiet":"",
        "NguonGocHinhThanh":"",
        "ThoiDiemHinhThanh":"",
        "SoHieuToBanDoGoc":"",
        "ChuaGiaoDat":"True",
        "ThuaDatId":"1",
        "SoHieuThua2":"",
        "ToBDCu":"",
        "TCTCu":"",
        "DienTichCu":"0.0",
        "LoaiDatCu":"",
        "GhiChu2":"",
        "DTPhapLy":"550.5",
        "MaChuSDID":"0",
        "LoaiDatKiemKe":"",
        "KyHieuDTSD":"",
        "maThua":"",
        "inSoLieuCu":"False",
        "hangDat":"0",
        "trangThai":"False",
        "saoLuuId":"0",
        "taiLieuDoDacId":"0",
        "sttThuaGoc":"",
        "maThua_clean":"1",
        "latitude":10.2309133,
        "longitude":103.9729587437,
        "polygon":[
            [
                10.2309765923,
                103.9730198669
            ],
            [
                10.2310612167,
                103.9730000156
            ],
            [
                10.2310615213,
                103.9730012692
            ],
            [
                10.2307908355,
                103.973067355
            ],
            [
                10.2307599892,
                103.972899442
            ],
            [
                10.2310290362,
                103.972867223
            ],
            [
                10.2310515904,
                103.972960184
            ],
            [
                10.2310050171,
                103.9729705472
            ],
            [
                10.2309962504,
                103.9729328997
            ],
            [
                10.2309581004,
                103.9729417591
            ],
            [
                10.2309577486,
                103.9729427089
            ],
            [
                10.2309755935,
                103.9730191714
            ],
            [
                10.2309765923,
                103.9730198669
            ]
        ]
    },
    {
        "index_right":"983",
        "Text_Clean":"23",
        "ID":"0",
        "ToBD":"23",
        "ThuaTam":"",
        "TCT":"23",
        "SHKhu":"",
        "SHKhoanh":"",
        "MaLD":"",
        "LRD":"CLN",
        "TTRung":"",
        "DienTichThuc":"189.41760000109207",
        "DienTich":"189.4",
        "dtThocu":"0.0",
        "DienTichThuHoi":"0.0",
        "TenChu":"Lương Bá Trung",
        "TenVC":"",
        "DTSD":"0",
        "DiaChi":"",
        "Xudong":"Khu phố 10",
        "TamX":"442250.39",
        "TamY":"1131328.1",
        "XMin":"0.0",
        "YMin":"0.0",
        "XMax":"0.0",
        "YMax":"0.0",
        "GhiChu":"DacapGCN",
        "CapNhat":"True",
        "LenPoly":"75.46",
        "DTMuonTam":"0.0",
        "MaXaID":"0",
        "KhuDanCu":"False",
        "DatDoThi":"False",
        "DiaChiThuaDatChiTiet":"",
        "NguonGocHinhThanh":"",
        "ThoiDiemHinhThanh":"",
        "SoHieuToBanDoGoc":"",
        "ChuaGiaoDat":"True",
        "ThuaDatId":"0",
        "SoHieuThua2":"",
        "ToBDCu":"",
        "TCTCu":"",
        "DienTichCu":"0.0",
        "LoaiDatCu":"",
        "GhiChu2":"",
        "DTPhapLy":"189.3",
        "MaChuSDID":"0",
        "LoaiDatKiemKe":"",
        "KyHieuDTSD":"",
        "maThua":"",
        "inSoLieuCu":"False",
        "hangDat":"0",
        "trangThai":"False",
        "saoLuuId":"0",
        "taiLieuDoDacId":"0",
        "sttThuaGoc":"",
        "maThua_clean":"23",
        "latitude":10.2308962013,
        "longitude":103.9728548308,
        "polygon":[
            [
                10.2309033907,
                103.9728536854
            ],
            [
                10.23090167,
                103.972851954
            ],
            [
                10.230935473,
                103.9728518982
            ],
            [
                10.2309389636,
                103.972876134
            ],
            [
                10.2307603519,
                103.972897516
            ],
            [
                10.2307522004,
                103.9728522006
            ],
            [
                10.230893055,
                103.9728519682
            ],
            [
                10.23089134,
                103.9728537053
            ],
            [
                10.2308858873,
                103.9728537319
            ],
            [
                10.2308852003,
                103.9728548932
            ],
            [
                10.230885978,
                103.9728555354
            ],
            [
                10.2308913429,
                103.9728555309
            ],
            [
                10.2308964725,
                103.9728606927
            ],
            [
                10.2308964856,
                103.9728661089
            ],
            [
                10.2308973867,
                103.9728669308
            ],
            [
                10.2308982852,
                103.972866106
            ],
            [
                10.2308982808,
                103.9728606897
            ],
            [
                10.2309033936,
                103.972855511
            ],
            [
                10.2309087586,
                103.9728554978
            ],
            [
                10.2309095555,
                103.9728547661
            ],
            [
                10.2309088434,
                103.972853694
            ],
            [
                10.2309033907,
                103.9728536854
            ]
        ]
    },
    {
        "index_right":"966",
        "Text_Clean":"5",
        "ID":"6",
        "ToBD":"23",
        "ThuaTam":"",
        "TCT":"5",
        "SHKhu":"",
        "SHKhoanh":"",
        "MaLD":"",
        "LRD":"ODT+CLN",
        "TTRung":"",
        "DienTichThuc":"487.7918874877505",
        "DienTich":"487.8",
        "dtThocu":"0.0",
        "DienTichThuHoi":"0.0",
        "TenChu":"Hồ Hữu Thừa",
        "TenVC":"",
        "DTSD":"0",
        "DiaChi":"",
        "Xudong":"Khu phố 10",
        "TamX":"442301.0",
        "TamY":"1131339.35",
        "XMin":"0.0",
        "YMin":"0.0",
        "XMax":"0.0",
        "YMax":"0.0",
        "GhiChu":"DacapGCN",
        "CapNhat":"True",
        "LenPoly":"98.45",
        "DTMuonTam":"0.0",
        "MaXaID":"0",
        "KhuDanCu":"False",
        "DatDoThi":"False",
        "DiaChiThuaDatChiTiet":"",
        "NguonGocHinhThanh":"",
        "ThoiDiemHinhThanh":"",
        "SoHieuToBanDoGoc":"",
        "ChuaGiaoDat":"True",
        "ThuaDatId":"6",
        "SoHieuThua2":"",
        "ToBDCu":"",
        "TCTCu":"",
        "DienTichCu":"0.0",
        "LoaiDatCu":"",
        "GhiChu2":"",
        "DTPhapLy":"532.6",
        "MaChuSDID":"0",
        "LoaiDatKiemKe":"",
        "KyHieuDTSD":"",
        "maThua":"",
        "inSoLieuCu":"False",
        "hangDat":"0",
        "trangThai":"False",
        "saoLuuId":"0",
        "taiLieuDoDacId":"0",
        "sttThuaGoc":"",
        "maThua_clean":"5",
        "latitude":10.2309937664,
        "longitude":103.9733175838,
        "polygon":[
            [
                10.2309888664,
                103.9733304625
            ],
            [
                10.23093039,
                103.9733441742
            ],
            [
                10.2309158693,
                103.9732814424
            ],
            [
                10.2311196762,
                103.973233658
            ],
            [
                10.2311359077,
                103.9732959887
            ],
            [
                10.2310007518,
                103.9733276773
            ],
            [
                10.2310007434,
                103.9733224827
            ],
            [
                10.2310058562,
                103.973317304
            ],
            [
                10.2310112212,
                103.9733172908
            ],
            [
                10.2310120352,
                103.973316381
            ],
            [
                10.2310112183,
                103.973315474
            ],
            [
                10.2310058533,
                103.9733154784
            ],
            [
                10.2310007237,
                103.9733103167
            ],
            [
                10.2310006974,
                103.9733048118
            ],
            [
                10.2309996331,
                103.9733040964
            ],
            [
                10.230998911,
                103.9733049034
            ],
            [
                10.2309989154,
                103.9733103197
            ],
            [
                10.2309938026,
                103.9733154983
            ],
            [
                10.2309884376,
                103.9733155116
            ],
            [
                10.2309876236,
                103.9733164213
            ],
            [
                10.2309884406,
                103.9733173283
            ],
            [
                10.2309938055,
                103.9733173239
            ],
            [
                10.2309989351,
                103.9733224857
            ],
            [
                10.2309989879,
                103.9733280908
            ],
            [
                10.2309906263,
                103.9733300513
            ],
            [
                10.2309895751,
                103.973329388
            ],
            [
                10.2309888664,
                103.9733304625
            ]
        ]
    },
    {
        "index_right":"967",
        "Text_Clean":"6",
        "ID":"7",
        "ToBD":"23",
        "ThuaTam":"",
        "TCT":"6",
        "SHKhu":"",
        "SHKhoanh":"",
        "MaLD":"",
        "LRD":"CLN",
        "TTRung":"",
        "DienTichThuc":"217.55820000357926",
        "DienTich":"217.6",
        "dtThocu":"0.0",
        "DienTichThuHoi":"0.0",
        "TenChu":"Võ Hoàng Minh",
        "TenVC":"",
        "DTSD":"0",
        "DiaChi":"",
        "Xudong":"Khu phố 10",
        "TamX":"442310.58",
        "TamY":"1131341.52",
        "XMin":"0.0",
        "YMin":"0.0",
        "XMax":"0.0",
        "YMax":"0.0",
        "GhiChu":"DacapGCN",
        "CapNhat":"True",
        "LenPoly":"84.67",
        "DTMuonTam":"0.0",
        "MaXaID":"0",
        "KhuDanCu":"False",
        "DatDoThi":"False",
        "DiaChiThuaDatChiTiet":"",
        "NguonGocHinhThanh":"",
        "ThoiDiemHinhThanh":"",
        "SoHieuToBanDoGoc":"",
        "ChuaGiaoDat":"True",
        "ThuaDatId":"7",
        "SoHieuThua2":"",
        "ToBDCu":"",
        "TCTCu":"",
        "DienTichCu":"0.0",
        "LoaiDatCu":"",
        "GhiChu2":"",
        "DTPhapLy":"217.7",
        "MaChuSDID":"0",
        "LoaiDatKiemKe":"",
        "KyHieuDTSD":"",
        "maThua":"",
        "inSoLieuCu":"False",
        "hangDat":"0",
        "trangThai":"False",
        "saoLuuId":"0",
        "taiLieuDoDacId":"0",
        "sttThuaGoc":"",
        "maThua_clean":"6",
        "latitude":10.231018396,
        "longitude":103.9734041663,
        "polygon":[
            [
                10.2310679892,
                103.9734179538
            ],
            [
                10.2311045346,
                103.9734099208
            ],
            [
                10.2308647131,
                103.9734694057
            ],
            [
                10.2308547535,
                103.9734174542
            ],
            [
                10.2311485782,
                103.9733446444
            ],
            [
                10.2311618732,
                103.9733956987
            ],
            [
                10.2311318819,
                103.9734031376
            ],
            [
                10.2311250271,
                103.9733692176
            ],
            [
                10.2311242275,
                103.973368503
            ],
            [
                10.2310607745,
                103.9733824072
            ],
            [
                10.2310600811,
                103.9733834818
            ],
            [
                10.2310669167,
                103.9734172437
            ],
            [
                10.2310679892,
                103.9734179538
            ]
        ]
    },
    {
        "index_right":"970",
        "Text_Clean":"9",
        "ID":"11",
        "ToBD":"23",
        "ThuaTam":"",
        "TCT":"9",
        "SHKhu":"",
        "SHKhoanh":"",
        "MaLD":"",
        "LRD":"CLN",
        "TTRung":"",
        "DienTichThuc":"476.9346500027459",
        "DienTich":"476.9",
        "dtThocu":"0.0",
        "DienTichThuHoi":"0.0",
        "TenChu":"Hồ Hữu Bảy",
        "TenVC":"",
        "DTSD":"0",
        "DiaChi":"",
        "Xudong":"Khu phố 10",
        "TamX":"442332.1",
        "TamY":"1131347.04",
        "XMin":"0.0",
        "YMin":"0.0",
        "XMax":"0.0",
        "YMax":"0.0",
        "GhiChu":"DacapGCN",
        "CapNhat":"True",
        "LenPoly":"101.54",
        "DTMuonTam":"0.0",
        "MaXaID":"0",
        "KhuDanCu":"False",
        "DatDoThi":"False",
        "DiaChiThuaDatChiTiet":"",
        "NguonGocHinhThanh":"",
        "ThoiDiemHinhThanh":"",
        "SoHieuToBanDoGoc":"",
        "ChuaGiaoDat":"True",
        "ThuaDatId":"11",
        "SoHieuThua2":"",
        "ToBDCu":"",
        "TCTCu":"",
        "DienTichCu":"0.0",
        "LoaiDatCu":"",
        "GhiChu2":"",
        "DTPhapLy":"477.1",
        "MaChuSDID":"0",
        "LoaiDatKiemKe":"",
        "KyHieuDTSD":"",
        "maThua":"",
        "inSoLieuCu":"False",
        "hangDat":"0",
        "trangThai":"False",
        "saoLuuId":"0",
        "taiLieuDoDacId":"0",
        "sttThuaGoc":"",
        "maThua_clean":"9",
        "latitude":10.2310733,
        "longitude":103.9736002601,
        "polygon":[
            [
                10.231170746,
                103.9735298308
            ],
            [
                10.2310791723,
                103.9735534879
            ],
            [
                10.2310762672,
                103.9735415961
            ],
            [
                10.2311922659,
                103.9735124103
            ],
            [
                10.2312233135,
                103.9736316364
            ],
            [
                10.2312142887,
                103.9736340792
            ],
            [
                10.2312128641,
                103.9736091866
            ],
            [
                10.23121227,
                103.9736083812
            ],
            [
                10.231165435,
                103.9736104232
            ],
            [
                10.2311646793,
                103.9736113644
            ],
            [
                10.2311667025,
                103.9736376045
            ],
            [
                10.2311986043,
                103.9736366877
            ],
            [
                10.2309044106,
                103.9736834645
            ],
            [
                10.2308871207,
                103.9735891862
            ],
            [
                10.2310444911,
                103.9735495912
            ],
            [
                10.2310584864,
                103.9736064199
            ],
            [
                10.2310594697,
                103.9736070164
            ],
            [
                10.2310676455,
                103.9736049629
            ],
            [
                10.2310689221,
                103.9736062475
            ],
            [
                10.2310689484,
                103.9736117523
            ],
            [
                10.2310700127,
                103.9736124677
            ],
            [
                10.2310707348,
                103.9736116608
            ],
            [
                10.2310707304,
                103.9736062445
            ],
            [
                10.2310734343,
                103.9736035057
            ],
            [
                10.2311825176,
                103.9735759752
            ],
            [
                10.2311828568,
                103.9735750208
            ],
            [
                10.2311718434,
                103.9735304894
            ],
            [
                10.231170746,
                103.9735298308
            ]
        ]
    },
    {
        "index_right":"971",
        "Text_Clean":"10",
        "ID":"12",
        "ToBD":"23",
        "ThuaTam":"",
        "TCT":"10",
        "SHKhu":"",
        "SHKhoanh":"",
        "MaLD":"",
        "LRD":"CLN",
        "TTRung":"",
        "DienTichThuc":"437.95979999937117",
        "DienTich":"438.0",
        "dtThocu":"0.0",
        "DienTichThuHoi":"0.0",
        "TenChu":"Hình Kiều Minh Phụng",
        "TenVC":"",
        "DTSD":"0",
        "DiaChi":"",
        "Xudong":"Khu phố 10",
        "TamX":"442343.57",
        "TamY":"1131349.7",
        "XMin":"0.0",
        "YMin":"0.0",
        "XMax":"0.0",
        "YMax":"0.0",
        "GhiChu":"DacapGCN",
        "CapNhat":"True",
        "LenPoly":"102.26",
        "DTMuonTam":"0.0",
        "MaXaID":"0",
        "KhuDanCu":"False",
        "DatDoThi":"False",
        "DiaChiThuaDatChiTiet":"",
        "NguonGocHinhThanh":"",
        "ThoiDiemHinhThanh":"",
        "SoHieuToBanDoGoc":"",
        "ChuaGiaoDat":"True",
        "ThuaDatId":"12",
        "SoHieuThua2":"",
        "ToBDCu":"",
        "TCTCu":"",
        "DienTichCu":"0.0",
        "LoaiDatCu":"",
        "GhiChu2":"",
        "DTPhapLy":"438.0",
        "MaChuSDID":"0",
        "LoaiDatKiemKe":"",
        "KyHieuDTSD":"",
        "maThua":"",
        "inSoLieuCu":"False",
        "hangDat":"0",
        "trangThai":"False",
        "saoLuuId":"0",
        "taiLieuDoDacId":"0",
        "sttThuaGoc":"",
        "maThua_clean":"10",
        "latitude":10.2310947268,
        "longitude":103.973704948,
        "polygon":[
            [
                10.2312136673,
                103.9736361369
            ],
            [
                10.2312237732,
                103.973633402
            ],
            [
                10.2312500675,
                103.9737343751
            ],
            [
                10.2309222794,
                103.9737764747
            ],
            [
                10.2309047479,
                103.973685259
            ],
            [
                10.2312136673,
                103.9736361369
            ]
        ]
    },
    {
        "index_right":"969",
        "Text_Clean":"8",
        "ID":"9",
        "ToBD":"23",
        "ThuaTam":"",
        "TCT":"8",
        "SHKhu":"",
        "SHKhoanh":"",
        "MaLD":"",
        "LRD":"CLN",
        "TTRung":"",
        "DienTichThuc":"244.2170999973314",
        "DienTich":"244.2",
        "dtThocu":"0.0",
        "DienTichThuHoi":"0.0",
        "TenChu":"Nguyễn Quốc Dũng",
        "TenVC":"",
        "DTSD":"0",
        "DiaChi":"",
        "Xudong":"Khu phố 10",
        "TamX":"442323.04",
        "TamY":"1131344.52",
        "XMin":"0.0",
        "YMin":"0.0",
        "XMax":"0.0",
        "YMax":"0.0",
        "GhiChu":"DacapGCN",
        "CapNhat":"True",
        "LenPoly":"88.22",
        "DTMuonTam":"0.0",
        "MaXaID":"0",
        "KhuDanCu":"False",
        "DatDoThi":"False",
        "DiaChiThuaDatChiTiet":"",
        "NguonGocHinhThanh":"",
        "ThoiDiemHinhThanh":"",
        "SoHieuToBanDoGoc":"",
        "ChuaGiaoDat":"True",
        "ThuaDatId":"9",
        "SoHieuThua2":"",
        "ToBDCu":"",
        "TCTCu":"",
        "DienTichCu":"0.0",
        "LoaiDatCu":"",
        "GhiChu2":"",
        "DTPhapLy":"244.1",
        "MaChuSDID":"0",
        "LoaiDatKiemKe":"",
        "KyHieuDTSD":"",
        "maThua":"",
        "inSoLieuCu":"False",
        "hangDat":"0",
        "trangThai":"False",
        "saoLuuId":"0",
        "taiLieuDoDacId":"0",
        "sttThuaGoc":"",
        "maThua_clean":"8",
        "latitude":10.2310455435,
        "longitude":103.9735179258,
        "polygon":[
            [
                10.2308760911,
                103.9735308761
            ],
            [
                10.2311773349,
                103.9734550736
            ],
            [
                10.2311918061,
                103.9735106446
            ],
            [
                10.2308867856,
                103.9735873891
            ],
            [
                10.2308760911,
                103.9735308761
            ]
        ]
    },
    {
        "index_right":"978",
        "Text_Clean":"20",
        "ID":"24",
        "ToBD":"23",
        "ThuaTam":"",
        "TCT":"20",
        "SHKhu":"",
        "SHKhoanh":"",
        "MaLD":"",
        "LRD":"DTL",
        "TTRung":"",
        "DienTichThuc":"203.44336012832355",
        "DienTich":"203.4",
        "dtThocu":"0.0",
        "DienTichThuHoi":"0.0",
        "TenChu":"UBND phường quản lý",
        "TenVC":"",
        "DTSD":"0",
        "DiaChi":"",
        "Xudong":"Khu phố 10",
        "TamX":"442457.92",
        "TamY":"1131368.51",
        "XMin":"0.0",
        "YMin":"0.0",
        "XMax":"0.0",
        "YMax":"0.0",
        "GhiChu":"",
        "CapNhat":"True",
        "LenPoly":"83.83",
        "DTMuonTam":"0.0",
        "MaXaID":"0",
        "KhuDanCu":"False",
        "DatDoThi":"False",
        "DiaChiThuaDatChiTiet":"",
        "NguonGocHinhThanh":"",
        "ThoiDiemHinhThanh":"",
        "SoHieuToBanDoGoc":"",
        "ChuaGiaoDat":"True",
        "ThuaDatId":"24",
        "SoHieuThua2":"",
        "ToBDCu":"",
        "TCTCu":"",
        "DienTichCu":"0.0",
        "LoaiDatCu":"",
        "GhiChu2":"",
        "DTPhapLy":"203.5",
        "MaChuSDID":"0",
        "LoaiDatKiemKe":"",
        "KyHieuDTSD":"",
        "maThua":"",
        "inSoLieuCu":"False",
        "hangDat":"0",
        "trangThai":"False",
        "saoLuuId":"0",
        "taiLieuDoDacId":"0",
        "sttThuaGoc":"",
        "maThua_clean":"20",
        "latitude":10.2312585104,
        "longitude":103.9747502031,
        "polygon":[
            [
                10.2313834295,
                103.9747020998
            ],
            [
                10.2313832867,
                103.9746917645
            ],
            [
                10.2314242786,
                103.9746811284
            ],
            [
                10.2314248687,
                103.9747224662
            ],
            [
                10.2313839327,
                103.9747357605
            ],
            [
                10.231383818,
                103.9747289416
            ],
            [
                10.231382659,
                103.974728263
            ],
            [
                10.2313820329,
                103.9747290562
            ],
            [
                10.2313821326,
                103.9747363451
            ],
            [
                10.2311175343,
                103.9748222752
            ],
            [
                10.2311067319,
                103.9747639411
            ],
            [
                10.2313814849,
                103.9746922336
            ],
            [
                10.2313816444,
                103.9747022143
            ],
            [
                10.2313825415,
                103.9747029361
            ],
            [
                10.2313834295,
                103.9747020998
            ]
        ]
    },
    {
        "index_right":"1422",
        "Text_Clean":"19",
        "ID":"23",
        "ToBD":"23",
        "ThuaTam":"",
        "TCT":"19",
        "SHKhu":"",
        "SHKhoanh":"",
        "MaLD":"",
        "LRD":"ODT+CLN",
        "TTRung":"",
        "DienTichThuc":"2030.7635425981134",
        "DienTich":"2030.8",
        "dtThocu":"0.0",
        "DienTichThuHoi":"0.0",
        "TenChu":"Chí Chốc Sếnh",
        "TenVC":"",
        "DTSD":"0",
        "DiaChi":"",
        "Xudong":"Khu phố 10",
        "TamX":"442430.12",
        "TamY":"1131363.58",
        "XMin":"0.0",
        "YMin":"0.0",
        "XMax":"0.0",
        "YMax":"0.0",
        "GhiChu":"DacapGCN",
        "CapNhat":"True",
        "LenPoly":"180.41",
        "DTMuonTam":"0.0",
        "MaXaID":"0",
        "KhuDanCu":"False",
        "DatDoThi":"False",
        "DiaChiThuaDatChiTiet":"",
        "NguonGocHinhThanh":"",
        "ThoiDiemHinhThanh":"",
        "SoHieuToBanDoGoc":"",
        "ChuaGiaoDat":"True",
        "ThuaDatId":"23",
        "SoHieuThua2":"",
        "ToBDCu":"",
        "TCTCu":"",
        "DienTichCu":"0.0",
        "LoaiDatCu":"",
        "GhiChu2":"",
        "DTPhapLy":"2288.0",
        "MaChuSDID":"0",
        "LoaiDatKiemKe":"",
        "KyHieuDTSD":"",
        "maThua":"",
        "inSoLieuCu":"False",
        "hangDat":"0",
        "trangThai":"False",
        "saoLuuId":"0",
        "taiLieuDoDacId":"0",
        "sttThuaGoc":"",
        "maThua_clean":"19",
        "latitude":10.2312340917,
        "longitude":103.9744849023,
        "polygon":[
            [
                10.2311612328,
                103.9742645157
            ],
            [
                10.231375011,
                103.9742376347
            ],
            [
                10.2313814581,
                103.974690355
            ],
            [
                10.2311064008,
                103.974762142
            ],
            [
                10.2310175538,
                103.9742825248
            ],
            [
                10.2311612328,
                103.9742645157
            ]
        ]
    },
    {
        "index_right":"977",
        "Text_Clean":"25",
        "ID":"21",
        "ToBD":"23",
        "ThuaTam":"",
        "TCT":"25",
        "SHKhu":"",
        "SHKhoanh":"",
        "MaLD":"",
        "LRD":"DGT",
        "TTRung":"",
        "DienTichThuc":"46.70460000005551",
        "DienTich":"46.7",
        "dtThocu":"0.0",
        "DienTichThuHoi":"0.0",
        "TenChu":"UBND phường quản lý",
        "TenVC":"",
        "DTSD":"0",
        "DiaChi":"",
        "Xudong":"Khu phố 10",
        "TamX":"442398.54",
        "TamY":"1131384.73",
        "XMin":"0.0",
        "YMin":"0.0",
        "XMax":"0.0",
        "YMax":"0.0",
        "GhiChu":"",
        "CapNhat":"True",
        "LenPoly":"27.91",
        "DTMuonTam":"0.0",
        "MaXaID":"0",
        "KhuDanCu":"False",
        "DatDoThi":"False",
        "DiaChiThuaDatChiTiet":"",
        "NguonGocHinhThanh":"",
        "ThoiDiemHinhThanh":"",
        "SoHieuToBanDoGoc":"",
        "ChuaGiaoDat":"True",
        "ThuaDatId":"21",
        "SoHieuThua2":"",
        "ToBDCu":"",
        "TCTCu":"",
        "DienTichCu":"0.0",
        "LoaiDatCu":"",
        "GhiChu2":"",
        "DTPhapLy":"46.7",
        "MaChuSDID":"0",
        "LoaiDatKiemKe":"",
        "KyHieuDTSD":"",
        "maThua":"",
        "inSoLieuCu":"False",
        "hangDat":"0",
        "trangThai":"False",
        "saoLuuId":"0",
        "taiLieuDoDacId":"0",
        "sttThuaGoc":"",
        "maThua_clean":"25",
        "latitude":10.2314098632,
        "longitude":103.974206882,
        "polygon":[
            [
                10.2313859127,
                103.9742344028
            ],
            [
                10.2313766694,
                103.9742355846
            ],
            [
                10.2313698795,
                103.9741877177
            ],
            [
                10.2314380967,
                103.9741766439
            ],
            [
                10.2314530933,
                103.9742259377
            ],
            [
                10.2313859127,
                103.9742344028
            ]
        ]
    },
    {
        "index_right":"1062",
        "Text_Clean":"18",
        "ID":"22",
        "ToBD":"23",
        "ThuaTam":"",
        "TCT":"18",
        "SHKhu":"",
        "SHKhoanh":"",
        "MaLD":"",
        "LRD":"CLN",
        "TTRung":"",
        "DienTichThuc":"121.34539999812841",
        "DienTich":"121.3",
        "dtThocu":"0.0",
        "DienTichThuHoi":"0.0",
        "TenChu":"Võ Thị Kiều Nương",
        "TenVC":"",
        "DTSD":"0",
        "DiaChi":"",
        "Xudong":"Khu phố 10",
        "TamX":"442400.82",
        "TamY":"1131368.58",
        "XMin":"0.0",
        "YMin":"0.0",
        "XMax":"0.0",
        "YMax":"0.0",
        "GhiChu":"DacapGCN",
        "CapNhat":"True",
        "LenPoly":"58.02",
        "DTMuonTam":"0.0",
        "MaXaID":"0",
        "KhuDanCu":"False",
        "DatDoThi":"False",
        "DiaChiThuaDatChiTiet":"",
        "NguonGocHinhThanh":"",
        "ThoiDiemHinhThanh":"",
        "SoHieuToBanDoGoc":"",
        "ChuaGiaoDat":"True",
        "ThuaDatId":"22",
        "SoHieuThua2":"",
        "ToBDCu":"",
        "TCTCu":"",
        "DienTichCu":"0.0",
        "LoaiDatCu":"",
        "GhiChu2":"",
        "DTPhapLy":"121.3",
        "MaChuSDID":"0",
        "LoaiDatKiemKe":"",
        "KyHieuDTSD":"",
        "maThua":"",
        "inSoLieuCu":"False",
        "hangDat":"0",
        "trangThai":"False",
        "saoLuuId":"0",
        "taiLieuDoDacId":"0",
        "sttThuaGoc":"",
        "maThua_clean":"18",
        "latitude":10.231268252,
        "longitude":103.9742267709,
        "polygon":[
            [
                10.2311561972,
                103.9742223903
            ],
            [
                10.2313680939,
                103.9741880074
            ],
            [
                10.231374875,
                103.9742358121
            ],
            [
                10.2311618904,
                103.9742625933
            ],
            [
                10.2311561972,
                103.9742223903
            ]
        ]
    },
    {
        "index_right":"979",
        "Text_Clean":"21",
        "ID":"25",
        "ToBD":"23",
        "ThuaTam":"",
        "TCT":"21",
        "SHKhu":"",
        "SHKhoanh":"",
        "MaLD":"",
        "LRD":"CLN",
        "TTRung":"",
        "DienTichThuc":"682.6908531527442",
        "DienTich":"682.7",
        "dtThocu":"0.0",
        "DienTichThuHoi":"0.0",
        "TenChu":"Lương Xuân Thiết",
        "TenVC":"",
        "DTSD":"0",
        "DiaChi":"",
        "Xudong":"Khu phố 10",
        "TamX":"442470.87",
        "TamY":"1131369.28",
        "XMin":"0.0",
        "YMin":"0.0",
        "XMax":"0.0",
        "YMax":"0.0",
        "GhiChu":"DacapGCN",
        "CapNhat":"True",
        "LenPoly":"108.75",
        "DTMuonTam":"0.0",
        "MaXaID":"0",
        "KhuDanCu":"False",
        "DatDoThi":"False",
        "DiaChiThuaDatChiTiet":"",
        "NguonGocHinhThanh":"",
        "ThoiDiemHinhThanh":"",
        "SoHieuToBanDoGoc":"",
        "ChuaGiaoDat":"True",
        "ThuaDatId":"25",
        "SoHieuThua2":"",
        "ToBDCu":"",
        "TCTCu":"",
        "DienTichCu":"0.0",
        "LoaiDatCu":"",
        "GhiChu2":"",
        "DTPhapLy":"1302.1",
        "MaChuSDID":"0",
        "LoaiDatKiemKe":"",
        "KyHieuDTSD":"",
        "maThua":"",
        "inSoLieuCu":"False",
        "hangDat":"0",
        "trangThai":"False",
        "saoLuuId":"0",
        "taiLieuDoDacId":"0",
        "sttThuaGoc":"",
        "maThua_clean":"21",
        "latitude":10.2312905202,
        "longitude":103.9748629755,
        "polygon":[
            [
                10.2313852888,
                103.9749574353
            ],
            [
                10.2311435565,
                103.9749614544
            ],
            [
                10.2311178723,
                103.9748240831
            ],
            [
                10.2313821599,
                103.9747382539
            ],
            [
                10.2313833578,
                103.9748221658
            ],
            [
                10.2313793217,
                103.9748151747
            ],
            [
                10.2313739626,
                103.9748087589
            ],
            [
                10.2313675814,
                103.9748033801
            ],
            [
                10.2313603719,
                103.9747992017
            ],
            [
                10.2313525533,
                103.9747963506
            ],
            [
                10.2313443631,
                103.9747949136
            ],
            [
                10.2313361287,
                103.9747949271
            ],
            [
                10.2313279432,
                103.9747963911
            ],
            [
                10.2313201338,
                103.9747992678
            ],
            [
                10.2313129378,
                103.9748034699
            ],
            [
                10.231306574,
                103.9748088697
            ],
            [
                10.2313012356,
                103.9748153031
            ],
            [
                10.2312970849,
                103.9748225746
            ],
            [
                10.2312942479,
                103.9748304633
            ],
            [
                10.231292633,
                103.9748430055
            ],
            [
                10.2312933778,
                103.9748513643
            ],
            [
                10.2312955491,
                103.9748594655
            ],
            [
                10.2312990808,
                103.974867063
            ],
            [
                10.2313038656,
                103.9748739259
            ],
            [
                10.2313096977,
                103.9748797947
            ],
            [
                10.2313165111,
                103.9748846029
            ],
            [
                10.2313240481,
                103.9748881437
            ],
            [
                10.2313320795,
                103.9748903093
            ],
            [
                10.2313403615,
                103.9748910341
            ],
            [
                10.2313486422,
                103.9748902959
            ],
            [
                10.2313566702,
                103.9748881173
            ],
            [
                10.2313642015,
                103.9748845644
            ],
            [
                10.2313710073,
                103.9748797451
            ],
            [
                10.2313768808,
                103.9748738059
            ],
            [
                10.2313816435,
                103.9748669273
            ],
            [
                10.2313839308,
                103.9748623052
            ],
            [
                10.2313852888,
                103.9749574353
            ]
        ]
    },
    {
        "index_right":"980",
        "Text_Clean":"26",
        "ID":"26",
        "ToBD":"23",
        "ThuaTam":"",
        "TCT":"26",
        "SHKhu":"",
        "SHKhoanh":"",
        "MaLD":"",
        "LRD":"CLN",
        "TTRung":"",
        "DienTichThuc":"575.4092000006494",
        "DienTich":"575.4",
        "dtThocu":"0.0",
        "DienTichThuHoi":"0.0",
        "TenChu":"Nguyên Thanh Tùng",
        "TenVC":"",
        "DTSD":"0",
        "DiaChi":"",
        "Xudong":"Khu phố 10",
        "TamX":"442490.71",
        "TamY":"1131370.81",
        "XMin":"0.0",
        "YMin":"0.0",
        "XMax":"0.0",
        "YMax":"0.0",
        "GhiChu":"DacapGCN",
        "CapNhat":"True",
        "LenPoly":"98.46",
        "DTMuonTam":"0.0",
        "MaXaID":"0",
        "KhuDanCu":"False",
        "DatDoThi":"False",
        "DiaChiThuaDatChiTiet":"",
        "NguonGocHinhThanh":"",
        "ThoiDiemHinhThanh":"",
        "SoHieuToBanDoGoc":"",
        "ChuaGiaoDat":"True",
        "ThuaDatId":"26",
        "SoHieuThua2":"",
        "ToBDCu":"",
        "TCTCu":"",
        "DienTichCu":"0.0",
        "LoaiDatCu":"",
        "GhiChu2":"",
        "DTPhapLy":"575.7",
        "MaChuSDID":"0",
        "LoaiDatKiemKe":"",
        "KyHieuDTSD":"",
        "maThua":"",
        "inSoLieuCu":"False",
        "hangDat":"0",
        "trangThai":"False",
        "saoLuuId":"0",
        "taiLieuDoDacId":"0",
        "sttThuaGoc":"",
        "maThua_clean":"26",
        "latitude":10.2312946109,
        "longitude":103.9750457941,
        "polygon":[
            [
                10.231385982,
                103.9751313026
            ],
            [
                10.2311758673,
                103.9751316478
            ],
            [
                10.2311438979,
                103.9749632746
            ],
            [
                10.2313853149,
                103.9749592607
            ],
            [
                10.2313870241,
                103.975078994
            ],
            [
                10.231385982,
                103.9751313026
            ]
        ]
    },
    {
        "index_right":"964",
        "Text_Clean":"35",
        "ID":"3",
        "ToBD":"23",
        "ThuaTam":"",
        "TCT":"35",
        "SHKhu":"",
        "SHKhoanh":"",
        "MaLD":"",
        "LRD":"CLN",
        "TTRung":"",
        "DienTichThuc":"205.53928463393822",
        "DienTich":"205.5",
        "dtThocu":"0.0",
        "DienTichThuHoi":"0.0",
        "TenChu":"Võ Thị Thanh Tần",
        "TenVC":"",
        "DTSD":"0",
        "DiaChi":"",
        "Xudong":"Khu phố 10",
        "TamX":"442286.73",
        "TamY":"1131336.03",
        "XMin":"0.0",
        "YMin":"0.0",
        "XMax":"0.0",
        "YMax":"0.0",
        "GhiChu":"DacapGCN",
        "CapNhat":"True",
        "LenPoly":"80.59",
        "DTMuonTam":"0.0",
        "MaXaID":"0",
        "KhuDanCu":"False",
        "DatDoThi":"False",
        "DiaChiThuaDatChiTiet":"",
        "NguonGocHinhThanh":"",
        "ThoiDiemHinhThanh":"",
        "SoHieuToBanDoGoc":"",
        "ChuaGiaoDat":"True",
        "ThuaDatId":"3",
        "SoHieuThua2":"",
        "ToBDCu":"",
        "TCTCu":"",
        "DienTichCu":"0.0",
        "LoaiDatCu":"",
        "GhiChu2":"",
        "DTPhapLy":"205.7",
        "MaChuSDID":"0",
        "LoaiDatKiemKe":"",
        "KyHieuDTSD":"",
        "maThua":"",
        "inSoLieuCu":"False",
        "hangDat":"0",
        "trangThai":"False",
        "saoLuuId":"0",
        "taiLieuDoDacId":"0",
        "sttThuaGoc":"",
        "maThua_clean":"35",
        "latitude":10.230968789,
        "longitude":103.9731863921,
        "polygon":[
            [
                10.2309575488,
                103.9731867231
            ],
            [
                10.2309581219,
                103.9731853198
            ],
            [
                10.2309635746,
                103.9731852933
            ],
            [
                10.2309686875,
                103.9731801146
            ],
            [
                10.2309686831,
                103.9731746983
            ],
            [
                10.2309695815,
                103.9731738735
            ],
            [
                10.2309704826,
                103.9731746954
            ],
            [
                10.2309704957,
                103.9731801117
            ],
            [
                10.2309756253,
                103.9731852734
            ],
            [
                10.2309809903,
                103.973185269
            ],
            [
                10.2309818073,
                103.973186176
            ],
            [
                10.2309809932,
                103.9731870858
            ],
            [
                10.2309756283,
                103.973187099
            ],
            [
                10.2309705154,
                103.9731922777
            ],
            [
                10.2309705198,
                103.9731976939
            ],
            [
                10.2309696214,
                103.9731985187
            ],
            [
                10.2309687203,
                103.9731976969
            ],
            [
                10.2309687072,
                103.9731922806
            ],
            [
                10.2309635776,
                103.9731871189
            ],
            [
                10.2309575488,
                103.9731867231
            ]
        ]
    },
    {
        "index_right":"968",
        "Text_Clean":"7",
        "ID":"8",
        "ToBD":"23",
        "ThuaTam":"",
        "TCT":"7",
        "SHKhu":"",
        "SHKhoanh":"",
        "MaLD":"",
        "LRD":"CLN",
        "TTRung":"",
        "DienTichThuc":"243.10240000043996",
        "DienTich":"243.1",
        "dtThocu":"0.0",
        "DienTichThuHoi":"0.0",
        "TenChu":"Nguyễn Văn Tú",
        "TenVC":"",
        "DTSD":"0",
        "DiaChi":"",
        "Xudong":"Khu phố 10",
        "TamX":"442316.68",
        "TamY":"1131343.0",
        "XMin":"0.0",
        "YMin":"0.0",
        "XMax":"0.0",
        "YMax":"0.0",
        "GhiChu":"DacapGCN",
        "CapNhat":"True",
        "LenPoly":"87.09",
        "DTMuonTam":"0.0",
        "MaXaID":"0",
        "KhuDanCu":"False",
        "DatDoThi":"False",
        "DiaChiThuaDatChiTiet":"",
        "NguonGocHinhThanh":"",
        "ThoiDiemHinhThanh":"",
        "SoHieuToBanDoGoc":"",
        "ChuaGiaoDat":"True",
        "ThuaDatId":"8",
        "SoHieuThua2":"",
        "ToBDCu":"",
        "TCTCu":"",
        "DienTichCu":"0.0",
        "LoaiDatCu":"",
        "GhiChu2":"",
        "DTPhapLy":"243.0",
        "MaChuSDID":"0",
        "LoaiDatKiemKe":"",
        "KyHieuDTSD":"",
        "maThua":"",
        "inSoLieuCu":"False",
        "hangDat":"0",
        "trangThai":"False",
        "saoLuuId":"0",
        "taiLieuDoDacId":"0",
        "sttThuaGoc":"",
        "maThua_clean":"7",
        "latitude":10.2310312177,
        "longitude":103.9734600541,
        "polygon":[
            [
                10.2310105242,
                103.9734904324
            ],
            [
                10.2309993328,
                103.9734469442
            ],
            [
                10.2311466124,
                103.9734077317
            ],
            [
                10.2311578038,
                103.9734512199
            ],
            [
                10.2310105242,
                103.9734904324
            ]
        ]
    },
    {
        "index_right":"981",
        "Text_Clean":"24",
        "ID":"5",
        "ToBD":"23",
        "ThuaTam":"",
        "TCT":"24",
        "SHKhu":"",
        "SHKhoanh":"",
        "MaLD":"",
        "LRD":"DGT",
        "TTRung":"",
        "DienTichThuc":"261.17385260225274",
        "DienTich":"261.2",
        "dtThocu":"0.0",
        "DienTichThuHoi":"0.0",
        "TenChu":"UBND phường quản lý",
        "TenVC":"",
        "DTSD":"0",
        "DiaChi":"",
        "Xudong":"Khu phố 10",
        "TamX":"442299.63",
        "TamY":"1131358.73",
        "XMin":"0.0",
        "YMin":"0.0",
        "XMax":"0.0",
        "YMax":"0.0",
        "GhiChu":"",
        "CapNhat":"True",
        "LenPoly":"223.45",
        "DTMuonTam":"0.0",
        "MaXaID":"0",
        "KhuDanCu":"False",
        "DatDoThi":"False",
        "DiaChiThuaDatChiTiet":"",
        "NguonGocHinhThanh":"",
        "ThoiDiemHinhThanh":"",
        "SoHieuToBanDoGoc":"",
        "ChuaGiaoDat":"True",
        "ThuaDatId":"5",
        "SoHieuThua2":"",
        "ToBDCu":"",
        "TCTCu":"",
        "DienTichCu":"0.0",
        "LoaiDatCu":"",
        "GhiChu2":"",
        "DTPhapLy":"261.2",
        "MaChuSDID":"0",
        "LoaiDatKiemKe":"",
        "KyHieuDTSD":"",
        "maThua":"",
        "inSoLieuCu":"False",
        "hangDat":"0",
        "trangThai":"False",
        "saoLuuId":"0",
        "taiLieuDoDacId":"0",
        "sttThuaGoc":"",
        "maThua_clean":"24",
        "latitude":10.231184043,
        "longitude":103.973335459,
        "polygon":[
            [
                10.2311629322,
                103.9733040574
            ],
            [
                10.231163551,
                103.9733027308
            ],
            [
                10.2311690037,
                103.9733027043
            ],
            [
                10.2311741166,
                103.9732975256
            ],
            [
                10.2311741122,
                103.9732921093
            ],
            [
                10.2311750106,
                103.9732912845
            ],
            [
                10.2311759117,
                103.9732921064
            ],
            [
                10.2311759248,
                103.9732975227
            ],
            [
                10.2311810544,
                103.9733026844
            ],
            [
                10.2311864194,
                103.97330268
            ],
            [
                10.2311872364,
                103.973303587
            ],
            [
                10.2311864223,
                103.9733044968
            ],
            [
                10.2311810574,
                103.97330451
            ],
            [
                10.2311759445,
                103.9733096887
            ],
            [
                10.2311759489,
                103.973315105
            ],
            [
                10.2311750505,
                103.9733159298
            ],
            [
                10.2311741494,
                103.9733151079
            ],
            [
                10.2311741363,
                103.9733096917
            ],
            [
                10.2311690067,
                103.9733045299
            ],
            [
                10.2311629322,
                103.9733040574
            ]
        ]
    },
    {
        "index_right":"974",
        "Text_Clean":"33",
        "ID":"15",
        "ToBD":"23",
        "ThuaTam":"",
        "TCT":"33",
        "SHKhu":"",
        "SHKhoanh":"",
        "MaLD":"",
        "LRD":"CLN",
        "TTRung":"",
        "DienTichThuc":"1271.7527999982121",
        "DienTich":"1271.8",
        "dtThocu":"0.0",
        "DienTichThuHoi":"0.0",
        "TenChu":"Nguyễn Thị Tám",
        "TenVC":"",
        "DTSD":"0",
        "DiaChi":"",
        "Xudong":"Khu phố 10",
        "TamX":"442366.78",
        "TamY":"1131356.08",
        "XMin":"0.0",
        "YMin":"0.0",
        "XMax":"0.0",
        "YMax":"0.0",
        "GhiChu":"DacapGCN",
        "CapNhat":"True",
        "LenPoly":"189.5",
        "DTMuonTam":"0.0",
        "MaXaID":"0",
        "KhuDanCu":"False",
        "DatDoThi":"False",
        "DiaChiThuaDatChiTiet":"",
        "NguonGocHinhThanh":"",
        "ThoiDiemHinhThanh":"",
        "SoHieuToBanDoGoc":"",
        "ChuaGiaoDat":"True",
        "ThuaDatId":"15",
        "SoHieuThua2":"",
        "ToBDCu":"",
        "TCTCu":"",
        "DienTichCu":"0.0",
        "LoaiDatCu":"",
        "GhiChu2":"",
        "DTPhapLy":"1272.0",
        "MaChuSDID":"0",
        "LoaiDatKiemKe":"",
        "KyHieuDTSD":"",
        "maThua":"",
        "inSoLieuCu":"False",
        "hangDat":"0",
        "trangThai":"False",
        "saoLuuId":"0",
        "taiLieuDoDacId":"0",
        "sttThuaGoc":"",
        "maThua_clean":"33",
        "latitude":10.2311085592,
        "longitude":103.9739992004,
        "polygon":[
            [
                10.2312343187,
                103.9738940887
            ],
            [
                10.231219089,
                103.9739637252
            ],
            [
                10.2311574644,
                103.9739474148
            ],
            [
                10.2311755141,
                103.9738774213
            ],
            [
                10.2312343187,
                103.9738940887
            ]
        ]
    }
]