[
    {
        "index_right":"983",
        "Text_Clean":"3002",
        "ID":"10",
        "ToBD":"66",
        "ThuaTam":"",
        "TCT":"3002",
        "SHKhu":"",
        "SHKhoanh":"",
        "MaLD":"",
        "LRD":"DGT",
        "TTRung":"",
        "DienTichThuc":"4686.791557522491",
        "DienTich":"4686.8",
        "dtThocu":"0.0",
        "DienTichThuHoi":"0.0",
        "TenChu":"UBND phường quản lý",
        "TenVC":"",
        "DTSD":"0",
        "DiaChi":"",
        "Xudong":" Tổ 13, khu phố 5",
        "TamX":"442026.11",
        "TamY":"1130429.27",
        "XMin":"0.0",
        "YMin":"0.0",
        "XMax":"0.0",
        "YMax":"0.0",
        "GhiChu":"",
        "CapNhat":"True",
        "LenPoly":"396.74667",
        "DTMuonTam":"0.0",
        "MaXaID":"0",
        "KhuDanCu":"False",
        "DatDoThi":"False",
        "DiaChiThuaDatChiTiet":"",
        "NguonGocHinhThanh":"",
        "ThoiDiemHinhThanh":"",
        "SoHieuToBanDoGoc":"",
        "ChuaGiaoDat":"True",
        "ThuaDatId":"0",
        "SoHieuThua2":"",
        "ToBDCu":"",
        "TCTCu":"",
        "DienTichCu":"0.0",
        "LoaiDatCu":"",
        "GhiChu2":"",
        "DTPhapLy":"4686.8",
        "MaChuSDID":"0",
        "LoaiDatKiemKe":"",
        "KyHieuDTSD":"",
        "maThua":"",
        "inSoLieuCu":"False",
        "hangDat":"0",
        "trangThai":"False",
        "saoLuuId":"0",
        "taiLieuDoDacId":"0",
        "sttThuaGoc":"",
        "maThua_clean":"3002",
        "latitude":10.2227583289,
        "longitude":103.9707826384,
        "polygon":[
            [
                10.2209908269,
                103.9703929803
            ],
            [
                10.2209919745,
                103.9703919271
            ],
            [
                10.2212075588,
                103.9704575937
            ],
            [
                10.2212307881,
                103.970399068
            ],
            [
                10.2212265052,
                103.9703977933
            ],
            [
                10.2212231193,
                103.9703997768
            ],
            [
                10.2212225208,
                103.9703985666
            ],
            [
                10.2212242796,
                103.9703971371
            ],
            [
                10.2211591524,
                103.9703779739
            ],
            [
                10.2211585663,
                103.9703767575
            ],
            [
                10.2211596584,
                103.9703762213
            ],
            [
                10.2212314637,
                103.9703973658
            ],
            [
                10.2212435391,
                103.9703669421
            ],
            [
                10.2212445444,
                103.9703663844
            ],
            [
                10.2212452176,
                103.9703676211
            ],
            [
                10.2212332059,
                103.9703978843
            ],
            [
                10.2218556937,
                103.9705831414
            ],
            [
                10.2220494109,
                103.9705828207
            ],
            [
                10.2220493943,
                103.9705699526
            ],
            [
                10.2220502928,
                103.9705691278
            ],
            [
                10.2220511939,
                103.9705699496
            ],
            [
                10.2220512192,
                103.9705828177
            ],
            [
                10.2220879771,
                103.9705827569
            ],
            [
                10.2220947727,
                103.9705618622
            ],
            [
                10.221492151,
                103.9703825331
            ],
            [
                10.2214915394,
                103.9703813995
            ],
            [
                10.2214926623,
                103.9703807821
            ],
            [
                10.2220953377,
                103.9705601271
            ],
            [
                10.222116578,
                103.9704949918
            ],
            [
                10.2221393371,
                103.9704182547
            ],
            [
                10.222155997,
                103.9703732097
            ],
            [
                10.222156989,
                103.970372628
            ],
            [
                10.2221576911,
                103.9703738483
            ],
            [
                10.2221413607,
                103.9704180016
            ],
            [
                10.2224377697,
                103.9705226058
            ],
            [
                10.2224380517,
                103.9705235792
            ],
            [
                10.2224198001,
                103.9705822075
            ],
            [
                10.2225014784,
                103.9705820723
            ],
            [
                10.2225014619,
                103.9705692042
            ],
            [
                10.2225023603,
                103.9705683794
            ],
            [
                10.2225032614,
                103.9705692012
            ],
            [
                10.2225032867,
                103.9705820693
            ],
            [
                10.2229535459,
                103.9705813239
            ],
            [
                10.2229535294,
                103.9705684557
            ],
            [
                10.2229544278,
                103.9705676309
            ],
            [
                10.2229553289,
                103.9705684528
            ],
            [
                10.2229553542,
                103.9705813209
            ],
            [
                10.2234056134,
                103.9705805754
            ],
            [
                10.2234055969,
                103.9705677072
            ],
            [
                10.223406584,
                103.9705668867
            ],
            [
                10.2234073964,
                103.9705677043
            ],
            [
                10.2234074217,
                103.9705805724
            ],
            [
                10.2234201682,
                103.9705805557
            ],
            [
                10.2234209852,
                103.9705814627
            ],
            [
                10.2234201712,
                103.9705823724
            ],
            [
                10.2234074247,
                103.9705823979
            ],
            [
                10.223407686,
                103.9707432663
            ],
            [
                10.2234721756,
                103.9707397952
            ],
            [
                10.2234727796,
                103.9707406607
            ],
            [
                10.2234726486,
                103.9707670926
            ],
            [
                10.2236158038,
                103.9707485488
            ],
            [
                10.2236703476,
                103.9707436099
            ],
            [
                10.223670541,
                103.9707446052
            ],
            [
                10.2236697928,
                103.9707451622
            ],
            [
                10.2236160195,
                103.9707503613
            ],
            [
                10.2234727214,
                103.9707689237
            ],
            [
                10.223477607,
                103.9708212948
            ],
            [
                10.2235781525,
                103.9708175202
            ],
            [
                10.2236282682,
                103.9708097779
            ],
            [
                10.223629281,
                103.9708104543
            ],
            [
                10.2236285417,
                103.9708115824
            ],
            [
                10.2235782864,
                103.9708193418
            ],
            [
                10.2234777768,
                103.9708231152
            ],
            [
                10.2234827315,
                103.9708762271
            ],
            [
                10.2235479859,
                103.9708704509
            ],
            [
                10.2236037767,
                103.9708628274
            ],
            [
                10.2236047939,
                103.9708636095
            ],
            [
                10.2236040192,
                103.9708646365
            ],
            [
                10.2235482073,
                103.9708722628
            ],
            [
                10.223482901,
                103.9708780446
            ],
            [
                10.2234878733,
                103.9709313456
            ],
            [
                10.2236284432,
                103.9709112757
            ],
            [
                10.2236294483,
                103.9709119637
            ],
            [
                10.2236286964,
                103.9709130833
            ],
            [
                10.223488043,
                103.9709331651
            ],
            [
                10.2234954478,
                103.9710125415
            ],
            [
                10.2235630124,
                103.9710065609
            ],
            [
                10.2236115335,
                103.9709999308
            ],
            [
                10.2236123945,
                103.9709729659
            ],
            [
                10.2236132383,
                103.9709720843
            ],
            [
                10.2236142019,
                103.9709730241
            ],
            [
                10.2236133507,
                103.9709996825
            ],
            [
                10.2236220556,
                103.9709984974
            ],
            [
                10.2236229436,
                103.9709991131
            ],
            [
                10.223622297,
                103.9710002978
            ],
            [
                10.223613291,
                103.9710015328
            ],
            [
                10.2236050786,
                103.9712561476
            ],
            [
                10.2236106114,
                103.9714012584
            ],
            [
                10.2236293492,
                103.9713991393
            ],
            [
                10.2236302015,
                103.9714003898
            ],
            [
                10.2236294624,
                103.9714009591
            ],
            [
                10.2236098462,
                103.9714031822
            ],
            [
                10.2236088468,
                103.9714023769
            ],
            [
                10.2236032702,
                103.9712561206
            ],
            [
                10.2236114738,
                103.9710017811
            ],
            [
                10.2235631916,
                103.9710083775
            ],
            [
                10.2234956174,
                103.971014359
            ],
            [
                10.223495804,
                103.971016779
            ],
            [
                10.2234636347,
                103.9711729188
            ],
            [
                10.2234986077,
                103.9715599209
            ],
            [
                10.2234982041,
                103.9715607664
            ],
            [
                10.2234968069,
                103.9715600867
            ],
            [
                10.2234623687,
                103.9711790023
            ],
            [
                10.2234088108,
                103.9714363059
            ],
            [
                10.2234090839,
                103.9716047224
            ],
            [
                10.2235677765,
                103.9716191356
            ],
            [
                10.2235685946,
                103.9716199474
            ],
            [
                10.2235676148,
                103.9716209538
            ],
            [
                10.2235038511,
                103.9716151746
            ],
            [
                10.2235058901,
                103.9716449138
            ],
            [
                10.2235051319,
                103.9716458714
            ],
            [
                10.2234091449,
                103.9716423923
            ],
            [
                10.2234096431,
                103.9719497179
            ],
            [
                10.2234223896,
                103.9719497013
            ],
            [
                10.2234232066,
                103.9719506083
            ],
            [
                10.2234223925,
                103.971951518
            ],
            [
                10.223409646,
                103.9719515435
            ],
            [
                10.2234096755,
                103.9719697193
            ],
            [
                10.2235148879,
                103.9719734289
            ],
            [
                10.2235154667,
                103.9719742579
            ],
            [
                10.2235164346,
                103.9720135123
            ],
            [
                10.2235156415,
                103.9720144339
            ],
            [
                10.223409768,
                103.9720268235
            ],
            [
                10.2234100062,
                103.9721738462
            ],
            [
                10.2234629573,
                103.972167149
            ],
            [
                10.2234639735,
                103.9721680306
            ],
            [
                10.223463182,
                103.9721689604
            ],
            [
                10.2234100091,
                103.9721756857
            ],
            [
                10.2234101752,
                103.9722782462
            ],
            [
                10.2234147849,
                103.9723388254
            ],
            [
                10.2234131246,
                103.9724743977
            ],
            [
                10.2234683313,
                103.9729554137
            ],
            [
                10.2235523803,
                103.9729505514
            ],
            [
                10.2235690047,
                103.9729411033
            ],
            [
                10.2235702197,
                103.97294146
            ],
            [
                10.2236215056,
                103.9731998079
            ],
            [
                10.2236241653,
                103.9732167771
            ],
            [
                10.2236203898,
                103.9732345661
            ],
            [
                10.2234324018,
                103.9732310216
            ],
            [
                10.2232293288,
                103.9732222292
            ],
            [
                10.2229446608,
                103.9732297235
            ],
            [
                10.2228948879,
                103.9732185944
            ],
            [
                10.2228309197,
                103.9731757708
            ],
            [
                10.2226330166,
                103.9732295987
            ],
            [
                10.2224676118,
                103.9731861286
            ],
            [
                10.2223090778,
                103.9731546093
            ],
            [
                10.2222945957,
                103.9731636085
            ],
            [
                10.2220227419,
                103.973304635
            ],
            [
                10.2219316762,
                103.9733276787
            ],
            [
                10.2217292399,
                103.9733416238
            ],
            [
                10.2216853366,
                103.9733434308
            ],
            [
                10.2216405611,
                103.9733424999
            ],
            [
                10.2214698184,
                103.9733177626
            ],
            [
                10.2213821186,
                103.9732979105
            ],
            [
                10.2213693202,
                103.9733416557
            ],
            [
                10.2213683711,
                103.9733423062
            ],
            [
                10.221367586,
                103.9733411386
            ],
            [
                10.221380624,
                103.9732965744
            ],
            [
                10.2213944364,
                103.9732550565
            ],
            [
                10.2211999549,
                103.9729702865
            ],
            [
                10.2212005817,
                103.9734524421
            ],
            [
                10.2209053468,
                103.9734530665
            ],
            [
                10.2209042272,
                103.9728815991
            ],
            [
                10.2209050616,
                103.9728810343
            ],
            [
                10.2211387376,
                103.9728806491
            ],
            [
                10.2207277019,
                103.9722787803
            ],
            [
                10.2208110896,
                103.9721236019
            ],
            [
                10.2207303791,
                103.9721131368
            ],
            [
                10.2207295975,
                103.9721121152
            ],
            [
                10.2207306094,
                103.9721113262
            ],
            [
                10.2208120182,
                103.9721218818
            ],
            [
                10.2208260538,
                103.9720958317
            ],
            [
                10.2207357587,
                103.972084285
            ],
            [
                10.2207349686,
                103.9720833541
            ],
            [
                10.2207357207,
                103.9720824796
            ],
            [
                10.2208268109,
                103.9720940884
            ],
            [
                10.2208807919,
                103.9718902317
            ],
            [
                10.220922997,
                103.9717114427
            ],
            [
                10.2209682669,
                103.9715315824
            ],
            [
                10.2210380947,
                103.9711556636
            ],
            [
                10.2211454847,
                103.9707129581
            ],
            [
                10.2211452788,
                103.9705861429
            ],
            [
                10.2211325322,
                103.9705861596
            ],
            [
                10.2211317323,
                103.9705850745
            ],
            [
                10.2211325293,
                103.9705843429
            ],
            [
                10.2211452758,
                103.9705843174
            ],
            [
                10.2211452593,
                103.9705714493
            ],
            [
                10.2211461577,
                103.9705706246
            ],
            [
                10.2211470588,
                103.9705714464
            ],
            [
                10.2211470841,
                103.9705843144
            ],
            [
                10.2211767024,
                103.9705842654
            ],
            [
                10.221207008,
                103.9704593327
            ],
            [
                10.2209914522,
                103.9703936748
            ],
            [
                10.2209908269,
                103.9703929803
            ]
        ]
    },
    {
        "index_right":"1061",
        "Text_Clean":"2",
        "ID":"1",
        "ToBD":"66",
        "ThuaTam":"",
        "TCT":"2",
        "SHKhu":"",
        "SHKhoanh":"",
        "MaLD":"",
        "LRD":"ODT+CLN",
        "TTRung":"",
        "DienTichThuc":"5067.85050889384",
        "DienTich":"5067.9",
        "dtThocu":"0.0",
        "DienTichThuHoi":"0.0",
        "TenChu":"Hồ Luật",
        "TenVC":"",
        "DTSD":"0",
        "DiaChi":"",
        "Xudong":" Tổ 13, khu phố 5",
        "TamX":"442212.76",
        "TamY":"1130464.83",
        "XMin":"0.0",
        "YMin":"0.0",
        "XMax":"0.0",
        "YMax":"0.0",
        "GhiChu":"DacapGCN",
        "CapNhat":"True",
        "LenPoly":"306.229042",
        "DTMuonTam":"0.0",
        "MaXaID":"0",
        "KhuDanCu":"False",
        "DatDoThi":"False",
        "DiaChiThuaDatChiTiet":"",
        "NguonGocHinhThanh":"",
        "ThoiDiemHinhThanh":"",
        "SoHieuToBanDoGoc":"",
        "ChuaGiaoDat":"True",
        "ThuaDatId":"12",
        "SoHieuThua2":"",
        "ToBDCu":"",
        "TCTCu":"",
        "DienTichCu":"0.0",
        "LoaiDatCu":"",
        "GhiChu2":"",
        "DTPhapLy":"5149.8",
        "MaChuSDID":"0",
        "LoaiDatKiemKe":"",
        "KyHieuDTSD":"",
        "maThua":"",
        "inSoLieuCu":"False",
        "hangDat":"0",
        "trangThai":"False",
        "saoLuuId":"0",
        "taiLieuDoDacId":"0",
        "sttThuaGoc":"",
        "maThua_clean":"2",
        "latitude":10.2231256168,
        "longitude":103.9725578178,
        "polygon":[
            [
                10.2234092918,
                103.9728497061
            ],
            [
                10.2234093125,
                103.9728624848
            ],
            [
                10.2232368755,
                103.9728627691
            ],
            [
                10.2232379466,
                103.9728429821
            ],
            [
                10.2232371803,
                103.9728420596
            ],
            [
                10.2227179578,
                103.972778582
            ],
            [
                10.2227748482,
                103.9725150158
            ],
            [
                10.2227758199,
                103.9725140316
            ],
            [
                10.2227811849,
                103.9725140183
            ],
            [
                10.2227819818,
                103.9725132867
            ],
            [
                10.2227812697,
                103.9725122146
            ],
            [
                10.2227755193,
                103.9725119065
            ],
            [
                10.2228311842,
                103.9722540168
            ],
            [
                10.2233775861,
                103.9721902789
            ],
            [
                10.2234011562,
                103.9721836283
            ],
            [
                10.2234083671,
                103.9722783177
            ],
            [
                10.2234092918,
                103.9728497061
            ]
        ]
    },
    {
        "index_right":"998",
        "Text_Clean":"1",
        "ID":"0",
        "ToBD":"66",
        "ThuaTam":"",
        "TCT":"1",
        "SHKhu":"",
        "SHKhoanh":"",
        "MaLD":"",
        "LRD":"CLN",
        "TTRung":"",
        "DienTichThuc":"221.36176023585722",
        "DienTich":"221.4",
        "dtThocu":"0.0",
        "DienTichThuHoi":"0.0",
        "TenChu":"Phù Ái Bùi & Lê Văn Bảnh",
        "TenVC":"",
        "DTSD":"0",
        "DiaChi":"",
        "Xudong":" Tổ 13, khu phố 5",
        "TamX":"442155.32",
        "TamY":"1130497.58",
        "XMin":"0.0",
        "YMin":"0.0",
        "XMax":"0.0",
        "YMax":"0.0",
        "GhiChu":"DacapGCN",
        "CapNhat":"True",
        "LenPoly":"89.804055",
        "DTMuonTam":"0.0",
        "MaXaID":"0",
        "KhuDanCu":"False",
        "DatDoThi":"False",
        "DiaChiThuaDatChiTiet":"",
        "NguonGocHinhThanh":"",
        "ThoiDiemHinhThanh":"",
        "SoHieuToBanDoGoc":"",
        "ChuaGiaoDat":"True",
        "ThuaDatId":"7",
        "SoHieuThua2":"",
        "ToBDCu":"",
        "TCTCu":"",
        "DienTichCu":"0.0",
        "LoaiDatCu":"",
        "GhiChu2":"",
        "DTPhapLy":"221.4",
        "MaChuSDID":"0",
        "LoaiDatKiemKe":"",
        "KyHieuDTSD":"",
        "maThua":"",
        "inSoLieuCu":"False",
        "hangDat":"0",
        "trangThai":"False",
        "saoLuuId":"0",
        "taiLieuDoDacId":"0",
        "sttThuaGoc":"",
        "maThua_clean":"1",
        "latitude":10.2233617858,
        "longitude":103.972029567,
        "polygon":[
            [
                10.2234078701,
                103.9719714831
            ],
            [
                10.2234079571,
                103.9720251977
            ],
            [
                10.223320102,
                103.9720358871
            ],
            [
                10.2233201786,
                103.9721450188
            ],
            [
                10.2232598499,
                103.9721518279
            ],
            [
                10.2232978942,
                103.9719676713
            ],
            [
                10.2234078701,
                103.9719714831
            ]
        ]
    },
    {
        "index_right":"1021",
        "Text_Clean":"3",
        "ID":"2",
        "ToBD":"66",
        "ThuaTam":"",
        "TCT":"3",
        "SHKhu":"",
        "SHKhoanh":"",
        "MaLD":"",
        "LRD":"DGD",
        "TTRung":"",
        "DienTichThuc":"19573.006152996793",
        "DienTich":"19573.0",
        "dtThocu":"0.0",
        "DienTichThuHoi":"0.0",
        "TenChu":"Trường Trung học phổ thông Phú Quốc",
        "TenVC":"",
        "DTSD":"0",
        "DiaChi":"",
        "Xudong":" Tổ 13, khu phố 5",
        "TamX":"442105.42",
        "TamY":"1130412.27",
        "XMin":"0.0",
        "YMin":"0.0",
        "XMax":"0.0",
        "YMax":"0.0",
        "GhiChu":"",
        "CapNhat":"True",
        "LenPoly":"619.478074",
        "DTMuonTam":"0.0",
        "MaXaID":"0",
        "KhuDanCu":"False",
        "DatDoThi":"False",
        "DiaChiThuaDatChiTiet":"",
        "NguonGocHinhThanh":"",
        "ThoiDiemHinhThanh":"",
        "SoHieuToBanDoGoc":"",
        "ChuaGiaoDat":"True",
        "ThuaDatId":"3",
        "SoHieuThua2":"",
        "ToBDCu":"",
        "TCTCu":"",
        "DienTichCu":"0.0",
        "LoaiDatCu":"",
        "GhiChu2":"",
        "DTPhapLy":"19573.0",
        "MaChuSDID":"0",
        "LoaiDatKiemKe":"",
        "KyHieuDTSD":"",
        "maThua":"",
        "inSoLieuCu":"False",
        "hangDat":"0",
        "trangThai":"False",
        "saoLuuId":"0",
        "taiLieuDoDacId":"0",
        "sttThuaGoc":"",
        "maThua_clean":"3",
        "latitude":10.222686747,
        "longitude":103.9715984463,
        "polygon":[
            [
                10.2232809699,
                103.9720406535
            ],
            [
                10.223257963,
                103.9721520201
            ],
            [
                10.2228192453,
                103.9721877217
            ],
            [
                10.2223530327,
                103.9721718044
            ],
            [
                10.2222437213,
                103.97218696
            ],
            [
                10.2221350926,
                103.9721974792
            ],
            [
                10.2219192991,
                103.9722022302
            ],
            [
                10.2220648494,
                103.9714973829
            ],
            [
                10.2220662469,
                103.9714966459
            ],
            [
                10.2220652265,
                103.9714955568
            ],
            [
                10.2221771364,
                103.970953612
            ],
            [
                10.2222896902,
                103.9709646358
            ],
            [
                10.222325774,
                103.9708204962
            ],
            [
                10.2226259177,
                103.9709093862
            ],
            [
                10.2226294788,
                103.9709185968
            ],
            [
                10.2229742455,
                103.9710012121
            ],
            [
                10.2231730842,
                103.97102781
            ],
            [
                10.2232016255,
                103.9710266393
            ],
            [
                10.2232754009,
                103.9710276739
            ],
            [
                10.2234063307,
                103.9710222533
            ],
            [
                10.2234063545,
                103.9710369572
            ],
            [
                10.223393608,
                103.9710369827
            ],
            [
                10.223392794,
                103.9710378924
            ],
            [
                10.223393611,
                103.9710387994
            ],
            [
                10.2234063575,
                103.9710387827
            ],
            [
                10.2234070022,
                103.9714361177
            ],
            [
                10.2233723919,
                103.9716021892
            ],
            [
                10.2233338067,
                103.9717826143
            ],
            [
                10.2232809699,
                103.9720406535
            ]
        ]
    },
    {
        "index_right":"1015",
        "Text_Clean":"5",
        "ID":"3",
        "ToBD":"66",
        "ThuaTam":"",
        "TCT":"5",
        "SHKhu":"",
        "SHKhoanh":"",
        "MaLD":"",
        "LRD":"CLN",
        "TTRung":"",
        "DienTichThuc":"3477.809631248936",
        "DienTich":"3477.8",
        "dtThocu":"0.0",
        "DienTichThuHoi":"0.0",
        "TenChu":"Hà Văn An",
        "TenVC":"",
        "DTSD":"0",
        "DiaChi":"",
        "Xudong":" Tổ 13, khu phố 5",
        "TamX":"442196.53",
        "TamY":"1130350.31",
        "XMin":"0.0",
        "YMin":"0.0",
        "XMax":"0.0",
        "YMax":"0.0",
        "GhiChu":"DacapGCN",
        "CapNhat":"True",
        "LenPoly":"260.304013",
        "DTMuonTam":"0.0",
        "MaXaID":"0",
        "KhuDanCu":"False",
        "DatDoThi":"False",
        "DiaChiThuaDatChiTiet":"",
        "NguonGocHinhThanh":"",
        "ThoiDiemHinhThanh":"",
        "SoHieuToBanDoGoc":"",
        "ChuaGiaoDat":"True",
        "ThuaDatId":"9",
        "SoHieuThua2":"",
        "ToBDCu":"",
        "TCTCu":"",
        "DienTichCu":"0.0",
        "LoaiDatCu":"",
        "GhiChu2":"",
        "DTPhapLy":"3477.8",
        "MaChuSDID":"0",
        "LoaiDatKiemKe":"",
        "KyHieuDTSD":"",
        "maThua":"",
        "inSoLieuCu":"False",
        "hangDat":"0",
        "trangThai":"False",
        "saoLuuId":"0",
        "taiLieuDoDacId":"0",
        "sttThuaGoc":"",
        "maThua_clean":"5",
        "latitude":10.2220829454,
        "longitude":103.9723772525,
        "polygon":[
            [
                10.221910546,
                103.972244618
            ],
            [
                10.2219179263,
                103.9722088782
            ],
            [
                10.2221832575,
                103.9721971842
            ],
            [
                10.2223531142,
                103.9721736313
            ],
            [
                10.2224916293,
                103.9721782963
            ],
            [
                10.2224893096,
                103.9722203514
            ],
            [
                10.2224655791,
                103.9725465917
            ],
            [
                10.221811481,
                103.9725557769
            ],
            [
                10.221910546,
                103.972244618
            ]
        ]
    },
    {
        "index_right":"955",
        "Text_Clean":"6003",
        "ID":"13",
        "ToBD":"66",
        "ThuaTam":"",
        "TCT":"6003",
        "SHKhu":"",
        "SHKhoanh":"",
        "MaLD":"",
        "LRD":"SON",
        "TTRung":"",
        "DienTichThuc":"24421.094600791577",
        "DienTich":"24421.1",
        "dtThocu":"0.0",
        "DienTichThuHoi":"0.0",
        "TenChu":"UBND phường quản lý",
        "TenVC":"",
        "DTSD":"0",
        "DiaChi":"",
        "Xudong":" Tổ 13, khu phố 5",
        "TamX":"442141.84",
        "TamY":"1130276.16",
        "XMin":"0.0",
        "YMin":"0.0",
        "XMax":"0.0",
        "YMax":"0.0",
        "GhiChu":"",
        "CapNhat":"True",
        "LenPoly":"719.479017",
        "DTMuonTam":"0.0",
        "MaXaID":"0",
        "KhuDanCu":"False",
        "DatDoThi":"False",
        "DiaChiThuaDatChiTiet":"",
        "NguonGocHinhThanh":"",
        "ThoiDiemHinhThanh":"",
        "SoHieuToBanDoGoc":"",
        "ChuaGiaoDat":"True",
        "ThuaDatId":"5",
        "SoHieuThua2":"",
        "ToBDCu":"",
        "TCTCu":"",
        "DienTichCu":"0.0",
        "LoaiDatCu":"",
        "GhiChu2":"",
        "DTPhapLy":"24421.1",
        "MaChuSDID":"0",
        "LoaiDatKiemKe":"",
        "KyHieuDTSD":"",
        "maThua":"",
        "inSoLieuCu":"False",
        "hangDat":"0",
        "trangThai":"False",
        "saoLuuId":"0",
        "taiLieuDoDacId":"0",
        "sttThuaGoc":"",
        "maThua_clean":"6003",
        "latitude":10.2213877256,
        "longitude":103.971718485,
        "polygon":[
            [
                10.2219945772,
                103.9709342284
            ],
            [
                10.2217337119,
                103.9721975095
            ],
            [
                10.2216185829,
                103.9725591052
            ],
            [
                10.2215195553,
                103.9728655999
            ],
            [
                10.2211507823,
                103.9728662077
            ],
            [
                10.2211500469,
                103.9724116545
            ],
            [
                10.2211627934,
                103.972411629
            ],
            [
                10.2211636074,
                103.9724107193
            ],
            [
                10.2211627905,
                103.9724098123
            ],
            [
                10.2211500439,
                103.972409829
            ],
            [
                10.2211493079,
                103.9719552758
            ],
            [
                10.2211620544,
                103.9719552503
            ],
            [
                10.2211628684,
                103.9719543406
            ],
            [
                10.2211620514,
                103.9719534336
            ],
            [
                10.2211493049,
                103.9719534503
            ],
            [
                10.2211485682,
                103.9714988971
            ],
            [
                10.2211613147,
                103.9714988717
            ],
            [
                10.2211621288,
                103.971497962
            ],
            [
                10.2211613118,
                103.9714970549
            ],
            [
                10.2211485653,
                103.9714970716
            ],
            [
                10.221147828,
                103.9710425185
            ],
            [
                10.2211605745,
                103.971042493
            ],
            [
                10.2211613885,
                103.9710415833
            ],
            [
                10.2211605715,
                103.9710406763
            ],
            [
                10.221147825,
                103.971040693
            ],
            [
                10.2211472933,
                103.9707131769
            ],
            [
                10.2211781219,
                103.9705860886
            ],
            [
                10.221588118,
                103.9705854099
            ],
            [
                10.22203874,
                103.9707345082
            ],
            [
                10.2219945772,
                103.9709342284
            ]
        ]
    },
    {
        "index_right":"1258",
        "Text_Clean":"8",
        "ID":"5",
        "ToBD":"66",
        "ThuaTam":"",
        "TCT":"8",
        "SHKhu":"",
        "SHKhoanh":"",
        "MaLD":"",
        "LRD":"CLN",
        "TTRung":"",
        "DienTichThuc":"666.6026421912247",
        "DienTich":"666.6",
        "dtThocu":"0.0",
        "DienTichThuHoi":"0.0",
        "TenChu":"Phù Thị Quốc",
        "TenVC":"",
        "DTSD":"0",
        "DiaChi":"",
        "Xudong":" Tổ 13, khu phố 5",
        "TamX":"442029.94",
        "TamY":"1130362.36",
        "XMin":"0.0",
        "YMin":"0.0",
        "XMax":"0.0",
        "YMax":"0.0",
        "GhiChu":"",
        "CapNhat":"True",
        "LenPoly":"106.402241",
        "DTMuonTam":"0.0",
        "MaXaID":"0",
        "KhuDanCu":"False",
        "DatDoThi":"False",
        "DiaChiThuaDatChiTiet":"",
        "NguonGocHinhThanh":"",
        "ThoiDiemHinhThanh":"",
        "SoHieuToBanDoGoc":"",
        "ChuaGiaoDat":"True",
        "ThuaDatId":"1",
        "SoHieuThua2":"",
        "ToBDCu":"",
        "TCTCu":"",
        "DienTichCu":"0.0",
        "LoaiDatCu":"",
        "GhiChu2":"",
        "DTPhapLy":"666.6",
        "MaChuSDID":"0",
        "LoaiDatKiemKe":"",
        "KyHieuDTSD":"",
        "maThua":"",
        "inSoLieuCu":"False",
        "hangDat":"0",
        "trangThai":"False",
        "saoLuuId":"0",
        "taiLieuDoDacId":"0",
        "sttThuaGoc":"",
        "maThua_clean":"8",
        "latitude":10.2221585675,
        "longitude":103.9708573429,
        "polygon":[
            [
                10.2220725698,
                103.9709412559
            ],
            [
                10.221996567,
                103.9709336085
            ],
            [
                10.2220404852,
                103.9707349949
            ],
            [
                10.2220427386,
                103.9707355199
            ],
            [
                10.2220433841,
                103.9707364617
            ],
            [
                10.2223240382,
                103.9708199795
            ],
            [
                10.2222883973,
                103.9709629725
            ],
            [
                10.2221775075,
                103.9709518147
            ],
            [
                10.2221885199,
                103.9708984849
            ],
            [
                10.2221877317,
                103.9708973911
            ],
            [
                10.2221867497,
                103.9708981123
            ],
            [
                10.222175698,
                103.9709516327
            ],
            [
                10.2220725698,
                103.9709412559
            ]
        ]
    },
    {
        "index_right":"952",
        "Text_Clean":"7",
        "ID":"14",
        "ToBD":"66",
        "ThuaTam":"",
        "TCT":"7",
        "SHKhu":"",
        "SHKhoanh":"",
        "MaLD":"",
        "LRD":"CLN",
        "TTRung":"",
        "DienTichThuc":"56.029433644842356",
        "DienTich":"56.0",
        "dtThocu":"0.0",
        "DienTichThuHoi":"0.0",
        "TenChu":"",
        "TenVC":"",
        "DTSD":"0",
        "DiaChi":"",
        "Xudong":" Tổ 13, khu phố 5",
        "TamX":"442114.35",
        "TamY":"1130502.98",
        "XMin":"0.0",
        "YMin":"0.0",
        "XMax":"0.0",
        "YMax":"0.0",
        "GhiChu":"",
        "CapNhat":"True",
        "LenPoly":"37.44",
        "DTMuonTam":"0.0",
        "MaXaID":"0",
        "KhuDanCu":"False",
        "DatDoThi":"False",
        "DiaChiThuaDatChiTiet":"",
        "NguonGocHinhThanh":"",
        "ThoiDiemHinhThanh":"",
        "SoHieuToBanDoGoc":"",
        "ChuaGiaoDat":"True",
        "ThuaDatId":"18",
        "SoHieuThua2":"",
        "ToBDCu":"",
        "TCTCu":"",
        "DienTichCu":"0.0",
        "LoaiDatCu":"",
        "GhiChu2":"",
        "DTPhapLy":"56.0",
        "MaChuSDID":"0",
        "LoaiDatKiemKe":"",
        "KyHieuDTSD":"",
        "maThua":"",
        "inSoLieuCu":"False",
        "hangDat":"0",
        "trangThai":"False",
        "saoLuuId":"0",
        "taiLieuDoDacId":"0",
        "sttThuaGoc":"",
        "maThua_clean":"7",
        "latitude":10.2234341965,
        "longitude":103.9716253978,
        "polygon":[
            [
                10.2234286163,
                103.9716412635
            ],
            [
                10.223409142,
                103.9716405655
            ],
            [
                10.2234090868,
                103.9716065556
            ],
            [
                10.2235020251,
                103.9716149793
            ],
            [
                10.2235040163,
                103.9716440214
            ],
            [
                10.2234286163,
                103.9716412635
            ]
        ]
    },
    {
        "index_right":"1067",
        "Text_Clean":"10",
        "ID":"7",
        "ToBD":"66",
        "ThuaTam":"",
        "TCT":"10",
        "SHKhu":"",
        "SHKhoanh":"",
        "MaLD":"",
        "LRD":"CLN",
        "TTRung":"",
        "DienTichThuc":"2641.0731671606773",
        "DienTich":"2641.1",
        "dtThocu":"0.0",
        "DienTichThuHoi":"0.0",
        "TenChu":"Đỗ Thu Hằng",
        "TenVC":"",
        "DTSD":"0",
        "DiaChi":"",
        "Xudong":" Tổ 13, khu phố 5",
        "TamX":"442263.03",
        "TamY":"1130471.72",
        "XMin":"0.0",
        "YMin":"0.0",
        "XMax":"0.0",
        "YMax":"0.0",
        "GhiChu":"DacapGCN",
        "CapNhat":"True",
        "LenPoly":"266.34695",
        "DTMuonTam":"0.0",
        "MaXaID":"0",
        "KhuDanCu":"False",
        "DatDoThi":"False",
        "DiaChiThuaDatChiTiet":"",
        "NguonGocHinhThanh":"",
        "ThoiDiemHinhThanh":"",
        "SoHieuToBanDoGoc":"",
        "ChuaGiaoDat":"True",
        "ThuaDatId":"15",
        "SoHieuThua2":"",
        "ToBDCu":"",
        "TCTCu":"",
        "DienTichCu":"0.0",
        "LoaiDatCu":"",
        "GhiChu2":"",
        "DTPhapLy":"2644.0",
        "MaChuSDID":"0",
        "LoaiDatKiemKe":"",
        "KyHieuDTSD":"",
        "maThua":"",
        "inSoLieuCu":"False",
        "hangDat":"0",
        "trangThai":"False",
        "saoLuuId":"0",
        "taiLieuDoDacId":"0",
        "sttThuaGoc":"",
        "maThua_clean":"10",
        "latitude":10.2231113264,
        "longitude":103.9729847378,
        "polygon":[
            [
                10.22323011,
                103.9729719459
            ],
            [
                10.2234667316,
                103.9729573372
            ],
            [
                10.2234676966,
                103.9729587767
            ],
            [
                10.2235406233,
                103.9729592369
            ],
            [
                10.2235529018,
                103.97295235
            ],
            [
                10.2235703821,
                103.9729513476
            ],
            [
                10.2236108307,
                103.9731552814
            ],
            [
                10.2231920464,
                103.9731397755
            ],
            [
                10.2227455431,
                103.9730432374
            ],
            [
                10.2226989484,
                103.9730414966
            ],
            [
                10.2226984763,
                103.9728885096
            ],
            [
                10.2227006789,
                103.9728654785
            ],
            [
                10.2229572478,
                103.9728650556
            ],
            [
                10.222957273,
                103.9728779237
            ],
            [
                10.2229581741,
                103.9728787455
            ],
            [
                10.2229590725,
                103.9728779207
            ],
            [
                10.2229590561,
                103.9728650526
            ],
            [
                10.2232349655,
                103.9728645977
            ],
            [
                10.2232292036,
                103.9729710003
            ],
            [
                10.22323011,
                103.9729719459
            ]
        ]
    },
    {
        "index_right":"1046",
        "Text_Clean":"12",
        "ID":"15",
        "ToBD":"66",
        "ThuaTam":"",
        "TCT":"12",
        "SHKhu":"",
        "SHKhoanh":"",
        "MaLD":"",
        "LRD":"CLN",
        "TTRung":"",
        "DienTichThuc":"5383.797716771718",
        "DienTich":"5383.8",
        "dtThocu":"0.0",
        "DienTichThuHoi":"0.0",
        "TenChu":"Phạm Thị Chính",
        "TenVC":"",
        "DTSD":"0",
        "DiaChi":"",
        "Xudong":" Tổ 13, khu phố 5",
        "TamX":"442275.18",
        "TamY":"1130400.18",
        "XMin":"0.0",
        "YMin":"0.0",
        "XMax":"0.0",
        "YMax":"0.0",
        "GhiChu":"",
        "CapNhat":"True",
        "LenPoly":"617.09",
        "DTMuonTam":"0.0",
        "MaXaID":"0",
        "KhuDanCu":"False",
        "DatDoThi":"False",
        "DiaChiThuaDatChiTiet":"",
        "NguonGocHinhThanh":"",
        "ThoiDiemHinhThanh":"",
        "SoHieuToBanDoGoc":"",
        "ChuaGiaoDat":"True",
        "ThuaDatId":"19",
        "SoHieuThua2":"",
        "ToBDCu":"",
        "TCTCu":"",
        "DienTichCu":"0.0",
        "LoaiDatCu":"",
        "GhiChu2":"",
        "DTPhapLy":"5362.6",
        "MaChuSDID":"0",
        "LoaiDatKiemKe":"",
        "KyHieuDTSD":"",
        "maThua":"",
        "inSoLieuCu":"False",
        "hangDat":"0",
        "trangThai":"False",
        "saoLuuId":"0",
        "taiLieuDoDacId":"0",
        "sttThuaGoc":"",
        "maThua_clean":"12",
        "latitude":10.2220318422,
        "longitude":103.9730367118,
        "polygon":[
            [
                10.2218144108,
                103.9730115837
            ],
            [
                10.2225152163,
                103.9730367304
            ],
            [
                10.2225152457,
                103.9730410312
            ],
            [
                10.2225161344,
                103.9730417636
            ],
            [
                10.2226459119,
                103.9730414194
            ],
            [
                10.2227452417,
                103.9730450391
            ],
            [
                10.2231918127,
                103.9731415892
            ],
            [
                10.2236111957,
                103.9731571217
            ],
            [
                10.2236195117,
                103.9731990494
            ],
            [
                10.2235660719,
                103.9731995666
            ],
            [
                10.2233443292,
                103.9731949759
            ],
            [
                10.2232635935,
                103.9731958478
            ],
            [
                10.2230532399,
                103.9731794637
            ],
            [
                10.2229427496,
                103.9732032766
            ],
            [
                10.2229117866,
                103.973194142
            ],
            [
                10.2228569507,
                103.9731501692
            ],
            [
                10.2228132929,
                103.9731404523
            ],
            [
                10.2227443685,
                103.9731640088
            ],
            [
                10.2226858447,
                103.9731792532
            ],
            [
                10.2226308173,
                103.973182144
            ],
            [
                10.2224169596,
                103.9731312291
            ],
            [
                10.2223077874,
                103.9731098418
            ],
            [
                10.2222445705,
                103.9731090437
            ],
            [
                10.2221984618,
                103.9731324879
            ],
            [
                10.2221763985,
                103.9731666077
            ],
            [
                10.2221207429,
                103.9732083105
            ],
            [
                10.2219872421,
                103.9732739755
            ],
            [
                10.2217067231,
                103.9733004732
            ],
            [
                10.2215069848,
                103.9732788117
            ],
            [
                10.2213971702,
                103.9732524237
            ],
            [
                10.2214234636,
                103.9731688934
            ],
            [
                10.2215208682,
                103.9728674232
            ],
            [
                10.2216010447,
                103.9728672911
            ],
            [
                10.2216010699,
                103.9728801592
            ],
            [
                10.221601971,
                103.972880981
            ],
            [
                10.2216028694,
                103.9728801562
            ],
            [
                10.221602853,
                103.9728672881
            ],
            [
                10.221826248,
                103.9728669199
            ],
            [
                10.2218136104,
                103.9730105966
            ],
            [
                10.2218144108,
                103.9730115837
            ]
        ]
    },
    {
        "index_right":"1009",
        "Text_Clean":"11",
        "ID":"8",
        "ToBD":"66",
        "ThuaTam":"",
        "TCT":"11",
        "SHKhu":"",
        "SHKhoanh":"",
        "MaLD":"",
        "LRD":"ODT+CLN",
        "TTRung":"",
        "DienTichThuc":"5475.276700520888",
        "DienTich":"5475.3",
        "dtThocu":"0.0",
        "DienTichThuHoi":"0.0",
        "TenChu":"Phạm Thị Chính",
        "TenVC":"",
        "DTSD":"0",
        "DiaChi":"",
        "Xudong":" Tổ 13, khu phố 5",
        "TamX":"442241.68",
        "TamY":"1130379.8",
        "XMin":"0.0",
        "YMin":"0.0",
        "XMax":"0.0",
        "YMax":"0.0",
        "GhiChu":"DacapGCN",
        "CapNhat":"True",
        "LenPoly":"378.00221",
        "DTMuonTam":"0.0",
        "MaXaID":"0",
        "KhuDanCu":"False",
        "DatDoThi":"False",
        "DiaChiThuaDatChiTiet":"",
        "NguonGocHinhThanh":"",
        "ThoiDiemHinhThanh":"",
        "SoHieuToBanDoGoc":"",
        "ChuaGiaoDat":"True",
        "ThuaDatId":"14",
        "SoHieuThua2":"",
        "ToBDCu":"",
        "TCTCu":"",
        "DienTichCu":"0.0",
        "LoaiDatCu":"",
        "GhiChu2":"",
        "DTPhapLy":"5475.0",
        "MaChuSDID":"0",
        "LoaiDatKiemKe":"",
        "KyHieuDTSD":"",
        "maThua":"",
        "inSoLieuCu":"False",
        "hangDat":"0",
        "trangThai":"False",
        "saoLuuId":"0",
        "taiLieuDoDacId":"0",
        "sttThuaGoc":"",
        "maThua_clean":"11",
        "latitude":10.2223142574,
        "longitude":103.9727584223,
        "polygon":[
            [
                10.2227072103,
                103.9727781875
            ],
            [
                10.2226990365,
                103.9728636557
            ],
            [
                10.2225069854,
                103.9728639723
            ],
            [
                10.2225069603,
                103.9728511041
            ],
            [
                10.2225060591,
                103.9728502823
            ],
            [
                10.2225051607,
                103.9728511071
            ],
            [
                10.2225051772,
                103.9728639752
            ],
            [
                10.2223189939,
                103.9728642821
            ],
            [
                10.2223259521,
                103.9728570346
            ],
            [
                10.22233341,
                103.9728462323
            ],
            [
                10.2223388697,
                103.9728343617
            ],
            [
                10.2223422315,
                103.9728216394
            ],
            [
                10.2223433539,
                103.972808521
            ],
            [
                10.222343055,
                103.9728018584
            ],
            [
                10.2223407829,
                103.9727889731
            ],
            [
                10.2223363085,
                103.9727766049
            ],
            [
                10.2223332484,
                103.9727706941
            ],
            [
                10.2223257443,
                103.9727599245
            ],
            [
                10.2223165623,
                103.9727506851
            ],
            [
                10.22230587,
                103.9727431446
            ],
            [
                10.2222940431,
                103.9727375931
            ],
            [
                10.222281441,
                103.9727341993
            ],
            [
                10.2222684466,
                103.9727330662
            ],
            [
                10.222261847,
                103.972733368
            ],
            [
                10.2222490834,
                103.9727356617
            ],
            [
                10.222242786,
                103.9727376776
            ],
            [
                10.2222309772,
                103.9727432681
            ],
            [
                10.2222203697,
                103.9727507925
            ],
            [
                10.2222155063,
                103.9727553063
            ],
            [
                10.2222071441,
                103.9727654113
            ],
            [
                10.2222006804,
                103.9727767564
            ],
            [
                10.2221981622,
                103.9727829223
            ],
            [
                10.2221948137,
                103.9727956482
            ],
            [
                10.2221937049,
                103.9728086881
            ],
            [
                10.2221940038,
                103.9728153507
            ],
            [
                10.2221962759,
                103.972828236
            ],
            [
                10.2222007503,
                103.9728406041
            ],
            [
                10.2222038104,
                103.9728465149
            ],
            [
                10.2222112637,
                103.9728572236
            ],
            [
                10.2222182452,
                103.9728644482
            ],
            [
                10.2220549177,
                103.9728647174
            ],
            [
                10.2220548926,
                103.9728518493
            ],
            [
                10.2220539914,
                103.9728510275
            ],
            [
                10.222053093,
                103.9728518523
            ],
            [
                10.2220531095,
                103.9728647204
            ],
            [
                10.2218282242,
                103.9728650911
            ],
            [
                10.2218553243,
                103.9725569869
            ],
            [
                10.2218897663,
                103.9725565032
            ],
            [
                10.2218920173,
                103.9727198716
            ],
            [
                10.2218929339,
                103.9727207716
            ],
            [
                10.22244458,
                103.9727130078
            ],
            [
                10.2224452953,
                103.9727121025
            ],
            [
                10.2224430444,
                103.9725487338
            ],
            [
                10.2224664027,
                103.9725484058
            ],
            [
                10.2226718983,
                103.9725590879
            ],
            [
                10.2226958856,
                103.9722343303
            ],
            [
                10.2227222467,
                103.9722359972
            ],
            [
                10.2228296778,
                103.9722487473
            ],
            [
                10.2228177874,
                103.9722618989
            ],
            [
                10.2228098861,
                103.9723024837
            ],
            [
                10.2227648508,
                103.9725111275
            ],
            [
                10.2227637663,
                103.9725122259
            ],
            [
                10.2227584013,
                103.9725122392
            ],
            [
                10.2227576044,
                103.9725129708
            ],
            [
                10.2227583165,
                103.9725140429
            ],
            [
                10.2227641393,
                103.9725144238
            ],
            [
                10.2227072103,
                103.9727781875
            ]
        ]
    },
    {
        "index_right":"973",
        "Text_Clean":"6001",
        "ID":"11",
        "ToBD":"66",
        "ThuaTam":"",
        "TCT":"6001",
        "SHKhu":"",
        "SHKhoanh":"",
        "MaLD":"",
        "LRD":"DTL",
        "TTRung":"",
        "DienTichThuc":"57.31275959854247",
        "DienTich":"57.3",
        "dtThocu":"0.0",
        "DienTichThuHoi":"0.0",
        "TenChu":"UBND phường quản lý",
        "TenVC":"",
        "DTSD":"0",
        "DiaChi":"",
        "Xudong":" Tổ 13, khu phố 5",
        "TamX":"442211.51",
        "TamY":"1130429.23",
        "XMin":"0.0",
        "YMin":"0.0",
        "XMax":"0.0",
        "YMax":"0.0",
        "GhiChu":"",
        "CapNhat":"True",
        "LenPoly":"120.508956",
        "DTMuonTam":"0.0",
        "MaXaID":"0",
        "KhuDanCu":"False",
        "DatDoThi":"False",
        "DiaChiThuaDatChiTiet":"",
        "NguonGocHinhThanh":"",
        "ThoiDiemHinhThanh":"",
        "SoHieuToBanDoGoc":"",
        "ChuaGiaoDat":"True",
        "ThuaDatId":"11",
        "SoHieuThua2":"",
        "ToBDCu":"",
        "TCTCu":"",
        "DienTichCu":"0.0",
        "LoaiDatCu":"",
        "GhiChu2":"",
        "DTPhapLy":"480.2",
        "MaChuSDID":"0",
        "LoaiDatKiemKe":"",
        "KyHieuDTSD":"",
        "maThua":"",
        "inSoLieuCu":"False",
        "hangDat":"0",
        "trangThai":"False",
        "saoLuuId":"0",
        "taiLieuDoDacId":"0",
        "sttThuaGoc":"",
        "maThua_clean":"6001",
        "latitude":10.2227692784,
        "longitude":103.9725157245,
        "polygon":[
            [
                10.2228116587,
                103.9723028449
            ],
            [
                10.2228195001,
                103.9722625587
            ],
            [
                10.2228299559,
                103.9722511336
            ],
            [
                10.2227739988,
                103.9725103766
            ],
            [
                10.2227706874,
                103.9725070444
            ],
            [
                10.2227706743,
                103.9725016283
            ],
            [
                10.2227699496,
                103.9725008237
            ],
            [
                10.2227688876,
                103.9725015426
            ],
            [
                10.2227688791,
                103.9725070474
            ],
            [
                10.2227672193,
                103.9725087285
            ],
            [
                10.2228116587,
                103.9723028449
            ]
        ]
    },
    {
        "index_right":"1003",
        "Text_Clean":"9",
        "ID":"6",
        "ToBD":"66",
        "ThuaTam":"",
        "TCT":"9",
        "SHKhu":"",
        "SHKhoanh":"",
        "MaLD":"",
        "LRD":"CLN",
        "TTRung":"",
        "DienTichThuc":"812.8969184588641",
        "DienTich":"812.9",
        "dtThocu":"0.0",
        "DienTichThuHoi":"0.0",
        "TenChu":"Phạm Thị Chính",
        "TenVC":"",
        "DTSD":"0",
        "DiaChi":"",
        "Xudong":" Tổ 13, khu phố 5",
        "TamX":"442197.97",
        "TamY":"1130408.34",
        "XMin":"0.0",
        "YMin":"0.0",
        "XMax":"0.0",
        "YMax":"0.0",
        "GhiChu":"DacapGCN",
        "CapNhat":"True",
        "LenPoly":"117.030836",
        "DTMuonTam":"0.0",
        "MaXaID":"0",
        "KhuDanCu":"False",
        "DatDoThi":"False",
        "DiaChiThuaDatChiTiet":"",
        "NguonGocHinhThanh":"",
        "ThoiDiemHinhThanh":"",
        "SoHieuToBanDoGoc":"",
        "ChuaGiaoDat":"True",
        "ThuaDatId":"10",
        "SoHieuThua2":"",
        "ToBDCu":"",
        "TCTCu":"",
        "DienTichCu":"0.0",
        "LoaiDatCu":"",
        "GhiChu2":"",
        "DTPhapLy":"812.9",
        "MaChuSDID":"0",
        "LoaiDatKiemKe":"",
        "KyHieuDTSD":"",
        "maThua":"",
        "inSoLieuCu":"False",
        "hangDat":"0",
        "trangThai":"False",
        "saoLuuId":"0",
        "taiLieuDoDacId":"0",
        "sttThuaGoc":"",
        "maThua_clean":"9",
        "latitude":10.222580655,
        "longitude":103.9723898911,
        "polygon":[
            [
                10.2226940807,
                103.9722342161
            ],
            [
                10.2226705408,
                103.9725573834
            ],
            [
                10.2224673894,
                103.97254663
            ],
            [
                10.2224910481,
                103.9722213777
            ],
            [
                10.2226940807,
                103.9722342161
            ]
        ]
    },
    {
        "index_right":"953",
        "Text_Clean":"3001",
        "ID":"9",
        "ToBD":"66",
        "ThuaTam":"",
        "TCT":"3001",
        "SHKhu":"",
        "SHKhoanh":"",
        "MaLD":"",
        "LRD":"DGT",
        "TTRung":"",
        "DienTichThuc":"569.8948367680568",
        "DienTich":"569.9",
        "dtThocu":"0.0",
        "DienTichThuHoi":"0.0",
        "TenChu":"UBND phường quản lý",
        "TenVC":"",
        "DTSD":"0",
        "DiaChi":"",
        "Xudong":" Tổ 13, khu phố 5",
        "TamX":"442178.19",
        "TamY":"1130448.79",
        "XMin":"0.0",
        "YMin":"0.0",
        "XMax":"0.0",
        "YMax":"0.0",
        "GhiChu":"",
        "CapNhat":"True",
        "LenPoly":"208.549154",
        "DTMuonTam":"0.0",
        "MaXaID":"0",
        "KhuDanCu":"False",
        "DatDoThi":"False",
        "DiaChiThuaDatChiTiet":"",
        "NguonGocHinhThanh":"",
        "ThoiDiemHinhThanh":"",
        "SoHieuToBanDoGoc":"",
        "ChuaGiaoDat":"True",
        "ThuaDatId":"8",
        "SoHieuThua2":"",
        "ToBDCu":"",
        "TCTCu":"",
        "DienTichCu":"0.0",
        "LoaiDatCu":"",
        "GhiChu2":"",
        "DTPhapLy":"569.9",
        "MaChuSDID":"0",
        "LoaiDatKiemKe":"",
        "KyHieuDTSD":"",
        "maThua":"",
        "inSoLieuCu":"False",
        "hangDat":"0",
        "trangThai":"False",
        "saoLuuId":"0",
        "taiLieuDoDacId":"0",
        "sttThuaGoc":"",
        "maThua_clean":"3001",
        "latitude":10.2229359808,
        "longitude":103.9722000046,
        "polygon":[
            [
                10.2228192356,
                103.9721895479
            ],
            [
                10.2232587826,
                103.9721537849
            ],
            [
                10.2233209393,
                103.9721467698
            ],
            [
                10.2233870911,
                103.9721767134
            ],
            [
                10.2228402894,
                103.9722374572
            ],
            [
                10.2228311951,
                103.9722470893
            ],
            [
                10.2227223843,
                103.9722341768
            ],
            [
                10.2224911646,
                103.9722195559
            ],
            [
                10.222493437,
                103.9721783578
            ],
            [
                10.2228192356,
                103.9721895479
            ]
        ]
    },
    {
        "index_right":"954",
        "Text_Clean":"6002",
        "ID":"12",
        "ToBD":"66",
        "ThuaTam":"",
        "TCT":"6002",
        "SHKhu":"",
        "SHKhoanh":"",
        "MaLD":"",
        "LRD":"SON",
        "TTRung":"",
        "DienTichThuc":"1107.020632399246",
        "DienTich":"1107.0",
        "dtThocu":"0.0",
        "DienTichThuHoi":"0.0",
        "TenChu":"UBND phường quản lý",
        "TenVC":"",
        "DTSD":"0",
        "DiaChi":"",
        "Xudong":" Tổ 13, khu phố 5",
        "TamX":"442283.8",
        "TamY":"1130399.52",
        "XMin":"0.0",
        "YMin":"0.0",
        "XMax":"0.0",
        "YMax":"0.0",
        "GhiChu":"",
        "CapNhat":"True",
        "LenPoly":"520.812078",
        "DTMuonTam":"0.0",
        "MaXaID":"0",
        "KhuDanCu":"False",
        "DatDoThi":"False",
        "DiaChiThuaDatChiTiet":"",
        "NguonGocHinhThanh":"",
        "ThoiDiemHinhThanh":"",
        "SoHieuToBanDoGoc":"",
        "ChuaGiaoDat":"True",
        "ThuaDatId":"17",
        "SoHieuThua2":"",
        "ToBDCu":"",
        "TCTCu":"",
        "DienTichCu":"0.0",
        "LoaiDatCu":"",
        "GhiChu2":"",
        "DTPhapLy":"1112.6",
        "MaChuSDID":"0",
        "LoaiDatKiemKe":"",
        "KyHieuDTSD":"",
        "maThua":"",
        "inSoLieuCu":"False",
        "hangDat":"0",
        "trangThai":"False",
        "saoLuuId":"0",
        "taiLieuDoDacId":"0",
        "sttThuaGoc":"",
        "maThua_clean":"6002",
        "latitude":10.2224168833,
        "longitude":103.9732270595,
        "polygon":[
            [
                10.222177662,
                103.97316793
            ],
            [
                10.2221996444,
                103.9731339102
            ],
            [
                10.2222447697,
                103.9731108718
            ],
            [
                10.2223075228,
                103.9731116495
            ],
            [
                10.2224165621,
                103.9731330101
            ],
            [
                10.2226306936,
                103.9731839741
            ],
            [
                10.2226862048,
                103.9731810447
            ],
            [
                10.2227449183,
                103.9731657483
            ],
            [
                10.2228132384,
                103.9731423049
            ],
            [
                10.2228561385,
                103.9731518269
            ],
            [
                10.2229108724,
                103.9731957347
            ],
            [
                10.2229426357,
                103.9732051266
            ],
            [
                10.2230533136,
                103.9731812966
            ],
            [
                10.223263494,
                103.973197671
            ],
            [
                10.2233443062,
                103.9731968014
            ],
            [
                10.2235660484,
                103.9732013921
            ],
            [
                10.2236198424,
                103.9732008718
            ],
            [
                10.223622343,
                103.9732167212
            ],
            [
                10.2236190295,
                103.97323298
            ],
            [
                10.2234324484,
                103.9732291966
            ],
            [
                10.2232293128,
                103.9732204035
            ],
            [
                10.2229448131,
                103.9732278977
            ],
            [
                10.2228956114,
                103.9732169043
            ],
            [
                10.2228310759,
                103.9731738693
            ],
            [
                10.2226330654,
                103.9732277433
            ],
            [
                10.2224680411,
                103.9731843551
            ],
            [
                10.22230885,
                103.9731527337
            ],
            [
                10.2222937382,
                103.9731620009
            ],
            [
                10.2220220347,
                103.97330295
            ],
            [
                10.2219313849,
                103.9733258734
            ],
            [
                10.2217291538,
                103.9733398003
            ],
            [
                10.2216853461,
                103.9733416051
            ],
            [
                10.2216406716,
                103.9733406765
            ],
            [
                10.2214701122,
                103.973315961
            ],
            [
                10.2213826675,
                103.9732961639
            ],
            [
                10.221396621,
                103.9732541683
            ],
            [
                10.2215067091,
                103.9732806175
            ],
            [
                10.2217067089,
                103.9733023033
            ],
            [
                10.2219876332,
                103.9732757701
            ],
            [
                10.2221216795,
                103.9732098767
            ],
            [
                10.222177662,
                103.97316793
            ]
        ]
    }
]